Workbook
Name Slicer_Diabetes_Status1: #N/A
Name Slicer_Weight_Status: #N/A

Sheet Customer Names
A1: Customer ID | B1: name
A2: Id1 | B2: Hawks, Ms. Kelly
A3: Id2 | B3: Lehner, Mr. Matthew D
A4: Id3 | B4: Lu, Mr. Phil
A5: Id4 | B5: Osborne, Ms. Kelsey
A6: Id5 | B6: Kadala, Ms. Kristyn
A7: Id6 | B7: Baker, Mr. Russell B.
A8: Id7 | B8: Macpherson, Mr. Scott
A9: Id8 | B9: Hallman, Mr. Stephen
A10: Id9 | B10: Moran, Mr. Patrick R.
A11: Id10 | B11: Benner, Ms. Brooke N.
A12: Id11 | B12: Fierro Vargas, Ms. Paola Andrea
... A2336: Id2335 | B2336: German, Mr. Aaron K

Sheet Medical Examinations
A1: Customer ID | B1: BMI | C1: HBA1C | D1: Heart Issues | E1: Any Transplants | F1: Cancer history | G1: NumberOfMajorSurgeries | H1: smoker | AS1: Customer ID | AT1: BMI | AU1: HBA1C | AV1: Any Transplants | AW1: Cancer history | AX1: Proper Heart Issues | AY1: Proper Smoker | AZ1: NumberOfMajorSurgeries2 | BA1: First Name | BB1: Diabetes Status | BC1: Weight Status
A2: Id1 | B2: 47.41 | C2: 7.47 | D2: No | E2: No | F2: No | G2: No major surgery | H2: yes | K2: 1.DATA CLEANING | AS2: Id1 | AT2: 47.41 | AU2: 7.47 | AV2: No | AW2: No | AX2: No | AY2: Yes | AZ2: 0 | BA2: Kelly | BB2: Diabetes | BC2: Obesity
A3: Id2 | B3: 30.36 | C3: 5.77 | D3: No | E3: No | F3: No | G3: No major surgery | H3: yes | AS3: Id2 | AT3: 30.36 | AU3: 5.77 | AV3: No | AW3: No | AX3: No | AY3: Yes | AZ3: 0 | BA3: Matthew D | BB3: Prediabetes | BC3: Obesity
A4: Id3 | B4: 34.485 | C4: 11.87 | D4: yes | E4: No | F4: No | G4: 2 | H4: yes | K4: Missing Values smoker | M4: =COUNTIF(H2:H2336,"?") -> 2 | R4: month | S4: year | U4: Proper Month | V4: Proper Year | AI4: State ID | AJ4: Proper Sate ID | AS4: Id3 | AT4: 34.485 | AU4: 11.87 | AV4: No | AW4: No | AX4: Yes | AY4: Yes | AZ4: 2 | BA4: Phil | BB4: Diabetes | BC4: Obesity
A5: Id4 | B5: 38.095 | C5: 6.05 | D5: No | E5: No | F5: No | G5: No major surgery | H5: yes | R5: Jul | S5: 1992 | U5: =SUBSTITUTE(R5,"?","Sep") -> Jul | V5: =IF(S5="?",ROUND(AVERAGEIF($S$5:$S$2347,"<>?"),0),S5) -> 1992 | AI5: R1013 | AJ5: =IF(AI5="?","Unknown",AI5) -> R1013 | AS5: Id4 | AT5: 38.095 | AU5: 6.05 | AV5: No | AW5: No | AX5: No | AY5: Yes | AZ5: 0 | BA5: Kelsey | BB5: Prediabetes | BC5: Obesity
A6: Id5 | B6: 35.53 | C6: 5.45 | D6: No | E6: No | F6: No | G6: No major surgery | H6: yes | K6: Missing Customer Id | M6: =COUNTIF('Hospitalisation Details'!A2:A2344,"?") -> 3 | R6: Nov | S6: 1992 | U6: =SUBSTITUTE(R6,"?","Sep") -> Nov | V6: =IF(S6="?",ROUND(AVERAGEIF($S$5:$S$2347,"<>?"),0),S6) -> 1992 | Y6: Mode | Z6: =INDEX($Y$9:$Y$2343,MODE(MATCH($Y$9:$Y$2343,$Y$9:$Y$2343,0))) -> No | AB6: Mode | AC6: =INDEX($AB$9:$AB$2348,MODE(MATCH(AB9:$AB$2348,$AB$9:$AB$2348,0))) -> tier - 2 | AE6: Mode | AF6: =INDEX($AE$9:$AE$2348,MODE(MATCH($AE$9:$AE$2348,$AE$9:$AE$2348,0))) -> tier - 2 | AI6: R1013 | AJ6: =IF(AI6="?","Unknown",AI6) -> R1013 | AS6: Id5 | AT6: 35.53 | AU6: 5.45 | AV6: No | AW6: No | AX6: No | AY6: Yes | AZ6: 0 | BA6: Kristyn | BB6: Normal | BC6: Obesity
A7: Id6 | B7: 32.8 | C7: 6.59 | D7: No | E7: No | F7: No | G7: No major surgery | H7: yes | R7: Jun | S7: 1993 | U7: =SUBSTITUTE(R7,"?","Sep") -> Jun | V7: =IF(S7="?",ROUND(AVERAGEIF($S$5:$S$2347,"<>?"),0),S7) -> 1993 | AI7: R1013 | AJ7: =IF(AI7="?","Unknown",AI7) -> R1013 | AS7: Id6 | AT7: 32.8 | AU7: 6.59 | AV7: No | AW7: No | AX7: No | AY7: Yes | AZ7: 0 | BA7: Russell B. | BB7: Diabetes | BC7: Obesity
A8: Id7 | B8: 36.4 | C8: 6.07 | D8: No | E8: No | F8: No | G8: No major surgery | H8: yes | K8: Missing year | M8: =COUNTIF('Hospitalisation Details'!B2:B2344,"?") -> 2 | R8: Sep | S8: 1992 | U8: =SUBSTITUTE(R8,"?","Sep") -> Sep | V8: =IF(S8="?",ROUND(AVERAGEIF($S$5:$S$2347,"<>?"),0),S8) -> 1992 | Y8: smoker | Z8: Proper Smoker | AB8: Hospital tier | AC8: Proper Hospital tier | AE8: City tier | AF8: Proper City tier | AI8: R1013 | AJ8: =IF(AI8="?","Unknown",AI8) -> R1013 | AS8: Id7 | AT8: 36.4 | AU8: 6.07 | AV8: No | AW8: No | AX8: No | AY8: Yes | AZ8: 0 | BA8: Scott | BB8: Prediabetes | BC8: Obesity
A9: Id8 | B9: 36.96 | C9: 7.93 | D9: No | E9: No | F9: No | G9: 3 | H9: yes | R9: Jul | S9: 1998 | U9: =SUBSTITUTE(R9,"?","Sep") -> Jul | V9: =IF(S9="?",ROUND(AVERAGEIF($S$5:$S$2347,"<>?"),0),S9) -> 1998 | Y9: yes | Z9: =IF(Y9="?",$Z$6,Y9) -> yes | AB9: tier - 2 | AC9: =IF(AB9="?",$AC$6,AB9) -> tier - 2 | AE9: tier - 3 | AF9: =IF(AE9="?",$AF$6,AE9) -> tier - 3 | AI9: R1013 | AJ9: =IF(AI9="?","Unknown",AI9) -> R1013 | AS9: Id8 | AT9: 36.96 | AU9: 7.93 | AV9: No | AW9: No | AX9: No | AY9: Yes | AZ9: 3 | BA9: Stephen | BB9: Diabetes | BC9: Obesity
A10: Id9 | B10: 41.14 | C10: 9.58 | D10: yes | E10: No | F10: Yes | G10: 1 | H10: yes | K10: Missing month | M10: =COUNTIF('Hospitalisation Details'!C2:C2344,"?") -> 3 | R10: Nov | S10: 2001 | U10: =SUBSTITUTE(R10,"?","Sep") -> Nov | V10: =IF(S10="?",ROUND(AVERAGEIF($S$5:$S$2347,"<>?"),0),S10) -> 2001 | Y10: yes | Z10: =IF(Y10="?",$Z$6,Y10) -> yes | AB10: tier - 2 | AC10: =IF(AB10="?",$AC$6,AB10) -> tier - 2 | AE10: tier - 1 | AF10: =IF(AE10="?",$AF$6,AE10) -> tier - 1 | AI10: R1012 | AJ10: =IF(AI10="?","Unknown",AI10) -> R1012 | AS10: Id9 | AT10: 41.14 | AU10: 9.58 | AV10: No | AW10: Yes | AX10: Yes | AY10: Yes | AZ10: 1 | BA10: Patrick R. | BB10: Diabetes | BC10: Obesity
A11: Id10 | B11: 38.06 | C11: 10.79 | D11: No | E11: No | F11: No | G11: No major surgery | H11: yes | R11: Jun | S11: 1993 | U11: =SUBSTITUTE(R11,"?","Sep") -> Jun | V11: =IF(S11="?",ROUND(AVERAGEIF($S$5:$S$2347,"<>?"),0),S11) -> 1993 | Y11: yes | Z11: =IF(Y11="?",$Z$6,Y11) -> yes | AB11: tier - 2 | AC11: =IF(AB11="?",$AC$6,AB11) -> tier - 2 | AE11: tier - 1 | AF11: =IF(AE11="?",$AF$6,AE11) -> tier - 1 | AI11: R1013 | AJ11: =IF(AI11="?","Unknown",AI11) -> R1013 | AS11: Id10 | AT11: 38.06 | AU11: 10.79 | AV11: No | AW11: No | AX11: No | AY11: Yes | AZ11: 0 | BA11: Brooke N. | BB11: Diabetes | BC11: Obesity
A12: Id11 | B12: 37.7 | C12: 5.96 | D12: yes | E12: No | F12: No | G12: 2 | H12: yes | K12: Missing Hospital tier | M12: =COUNTIF('Hospitalisation Details'!G2:G2344,"?") -> 1 | R12: Jul | S12: 1995 | U12: =SUBSTITUTE(R12,"?","Sep") -> Jul | V12: =IF(S12="?",ROUND(AVERAGEIF($S$5:$S$2347,"<>?"),0),S12) -> 1995 | Y12: yes | Z12: =IF(Y12="?",$Z$6,Y12) -> yes | AB12: tier - 3 | AC12: =IF(AB12="?",$AC$6,AB12) -> tier - 3 | AE12: tier - 3 | AF12: =IF(AE12="?",$AF$6,AE12) -> tier - 3 | AI12: R1013 | AJ12: =IF(AI12="?","Unknown",AI12) -> R1013 | AS12: Id11 | AT12: 37.7 | AU12: 5.96 | AV12: No | AW12: No | AX12: Yes | AY12: Yes | AZ12: 2 | BA12: Paola Andrea | BB12: Prediabetes | BC12: Obesity
A13: Id12 | B13: 42.13 | C13: 11.9 | D13: No | E13: No | F13: No | G13: No major surgery | H13: yes | R13: Nov | S13: 2002 | U13: =SUBSTITUTE(R13,"?","Sep") -> Nov | V13: =IF(S13="?",ROUND(AVERAGEIF($S$5:$S$2347,"<>?"),0),S13) -> 2002 | Y13: yes | Z13: =IF(Y13="?",$Z$6,Y13) -> yes | AB13: tier - 3 | AC13: =IF(AB13="?",$AC$6,AB13) -> tier - 3 | AE13: tier - 3 | AF13: =IF(AE13="?",$AF$6,AE13) -> tier - 3 | AI13: R1012 | AJ13: =IF(AI13="?","Unknown",AI13) -> R1012 | AS13: Id12 | AT13: 42.13 | AU13: 11.9 | AV13: No | AW13: No | AX13: No | AY13: Yes | AZ13: 0 | BA13: David | BB13: Diabetes | BC13: Obesity
A14: Id13 | B14: 40.92 | C14: 8.41 | D14: No | E14: No | F14: No | G14: No major surgery | H14: yes | K14: Missing city tier | M14: =COUNTIF('Hospitalisation Details'!H2:H2344,"?") -> 1 | R14: Nov | S14: 1997 | U14: =SUBSTITUTE(R14,"?","Sep") -> Nov | V14: =IF(S14="?",ROUND(AVERAGEIF($S$5:$S$2347,"<>?"),0),S14) -> 1997 | Y14: yes | Z14: =IF(Y14="?",$Z$6,Y14) -> yes | AB14: tier - 3 | AC14: =IF(AB14="?",$AC$6,AB14) -> tier - 3 | AE14: tier - 3 | AF14: =IF(AE14="?",$AF$6,AE14) -> tier - 3 | AI14: R1013 | AJ14: =IF(AI14="?","Unknown",AI14) -> R1013 | AS14: Id13 | AT14: 40.92 | AU14: 8.41 | AV14: No | AW14: No | AX14: No | AY14: Yes | AZ14: 0 | BA14: Wade | BB14: Diabetes | BC14: Obesity
A15: Id14 | B15: 40.565 | C15: 7.02 | D15: No | E15: No | F15: No | G15: No major surgery | H15: yes | R15: Sep | S15: 2001 | U15: =SUBSTITUTE(R15,"?","Sep") -> Sep | V15: =IF(S15="?",ROUND(AVERAGEIF($S$5:$S$2347,"<>?"),0),S15) -> 2001 | Y15: yes | Z15: =IF(Y15="?",$Z$6,Y15) -> yes | AB15: tier - 3 | AC15: =IF(AB15="?",$AC$6,AB15) -> tier - 3 | AE15: tier - 3 | AF15: =IF(AE15="?",$AF$6,AE15) -> tier - 3 | AI15: R1013 | AJ15: =IF(AI15="?","Unknown",AI15) -> R1013 | AS15: Id14 | AT15: 40.565 | AU15: 7.02 | AV15: No | AW15: No | AX15: No | AY15: Yes | AZ15: 0 | BA15: Franklin | BB15: Diabetes | BC15: Obesity
A16: Id15 | B16: 36.385 | C16: 7.59 | D16: yes | E16: No | F16: No | G16: 2 | H16: yes | K16: Missing state | M16: =COUNTIF('Hospitalisation Details'!I2:I2344,"?") -> 2 | R16: Dec | S16: 1999 | U16: =SUBSTITUTE(R16,"?","Sep") -> Dec | V16: =IF(S16="?",ROUND(AVERAGEIF($S$5:$S$2347,"<>?"),0),S16) -> 1999 | Y16: yes | Z16: =IF(Y16="?",$Z$6,Y16) -> yes | AB16: tier - 3 | AC16: =IF(AB16="?",$AC$6,AB16) -> tier - 3 | AE16: tier - 3 | AF16: =IF(AE16="?",$AF$6,AE16) -> tier - 3 | AI16: R1013 | AJ16: =IF(AI16="?","Unknown",AI16) -> R1013 | AS16: Id15 | AT16: 36.385 | AU16: 7.59 | AV16: No | AW16: No | AX16: Yes | AY16: Yes | AZ16: 2 | BA16: Leilani M. | BB16: Diabetes | BC16: Obesity
A17: Id16 | B17: 39.9 | C17: 11.32 | D17: No | E17: No | F17: No | G17: No major surgery | H17: yes | R17: Dec | S17: 1999 | U17: =SUBSTITUTE(R17,"?","Sep") -> Dec | V17: =IF(S17="?",ROUND(AVERAGEIF($S$5:$S$2347,"<>?"),0),S17) -> 1999 | Y17: yes | Z17: =IF(Y17="?",$Z$6,Y17) -> yes | AB17: tier - 3 | AC17: =IF(AB17="?",$AC$6,AB17) -> tier - 3 | AE17: tier - 2 | AF17: =IF(AE17="?",$AF$6,AE17) -> tier - 2 | AI17: R1013 | AJ17: =IF(AI17="?","Unknown",AI17) -> R1013 | AS17: Id16 | AT17: 39.9 | AU17: 11.32 | AV17: No | AW17: No | AX17: No | AY17: Yes | AZ17: 0 | BA17: Philippe | BB17: Diabetes | BC17: Obesity
A18: Id17 | B18: 33.8 | C18: 7.67 | D18: No | E18: No | F18: No | G18: 3 | H18: yes | R18: ? | S18: 2002 | U18: =SUBSTITUTE(R18,"?","Sep") -> Sep | V18: =IF(S18="?",ROUND(AVERAGEIF($S$5:$S$2347,"<>?"),0),S18) -> 2002 | Y18: yes | Z18: =IF(Y18="?",$Z$6,Y18) -> yes | AB18: tier - 3 | AC18: =IF(AB18="?",$AC$6,AB18) -> tier - 3 | AE18: tier - 3 | AF18: =IF(AE18="?",$AF$6,AE18) -> tier - 3 | AI18: R1012 | AJ18: =IF(AI18="?","Unknown",AI18) -> R1012 | AS18: Id17 | AT18: 33.8 | AU18: 7.67 | AV18: No | AW18: No | AX18: No | AY18: Yes | AZ18: 3 | BA18: Jennifer A. | BB18: Diabetes | BC18: Obesity
A19: Id18 | B19: 36.765 | C19: 7.29 | D19: yes | E19: No | F19: Yes | G19: 1 | H19: yes | R19: Aug | S19: 1993 | U19: =SUBSTITUTE(R19,"?","Sep") -> Aug | V19: =IF(S19="?",ROUND(AVERAGEIF($S$5:$S$2347,"<>?"),0),S19) -> 1993 | Y19: yes | Z19: =IF(Y19="?",$Z$6,Y19) -> yes | AB19: tier - 3 | AC19: =IF(AB19="?",$AC$6,AB19) -> tier - 3 | AE19: tier - 2 | AF19: =IF(AE19="?",$AF$6,AE19) -> tier - 2 | AI19: R1013 | AJ19: =IF(AI19="?","Unknown",AI19) -> R1013 | AS19: Id18 | AT19: 36.765 | AU19: 7.29 | AV19: No | AW19: Yes | AX19: Yes | AY19: Yes | AZ19: 1 | BA19: Christina M. | BB19: Diabetes | BC19: Obesity
A20: Id19 | B20: 36.955 | C20: 4.72 | D20: yes | E20: No | F20: No | G20: 1 | H20: yes | R20: Oct | S20: 1996 | U20: =SUBSTITUTE(R20,"?","Sep") -> Oct | V20: =IF(S20="?",ROUND(AVERAGEIF($S$5:$S$2347,"<>?"),0),S20) -> 1996 | Y20: yes | Z20: =IF(Y20="?",$Z$6,Y20) -> yes | AB20: ? | AC20: =IF(AB20="?",$AC$6,AB20) -> tier - 2 | AE20: tier - 3 | AF20: =IF(AE20="?",$AF$6,AE20) -> tier - 3 | AI20: R1013 | AJ20: =IF(AI20="?","Unknown",AI20) -> R1013 | AS20: Id19 | AT20: 36.955 | AU20: 4.72 | AV20: No | AW20: No | AX20: Yes | AY20: Yes | AZ20: 1 | BA20: Said Sr. | BB20: Normal | BC20: Obesity
A21: Id20 | B21: 42.9 | C21: 11.41 | D21: No | E21: No | F21: No | G21: No major surgery | H21: yes | R21: Jun | S21: 1993 | U21: =SUBSTITUTE(R21,"?","Sep") -> Jun | V21: =IF(S21="?",ROUND(AVERAGEIF($S$5:$S$2347,"<>?"),0),S21) -> 1993 | Y21: yes | Z21: =IF(Y21="?",$Z$6,Y21) -> yes | AB21: tier - 3 | AC21: =IF(AB21="?",$AC$6,AB21) -> tier - 3 | AE21: tier - 1 | AF21: =IF(AE21="?",$AF$6,AE21) -> tier - 1 | AI21: R1013 | AJ21: =IF(AI21="?","Unknown",AI21) -> R1013 | AS21: Id20 | AT21: 42.9 | AU21: 11.41 | AV21: No | AW21: No | AX21: No | AY21: Yes | AZ21: 0 | BA21: John | BB21: Diabetes | BC21: Obesity
A22: Id21 | B22: 36.3 | C22: 11.5 | D22: yes | E22: No | F22: No | G22: 2 | H22: yes | R22: ? | S22: 1996 | U22: =SUBSTITUTE(R22,"?","Sep") -> Sep | V22: =IF(S22="?",ROUND(AVERAGEIF($S$5:$S$2347,"<>?"),0),S22) -> 1996 | Y22: yes | Z22: =IF(Y22="?",$Z$6,Y22) -> yes | AB22: tier - 3 | AC22: =IF(AB22="?",$AC$6,AB22) -> tier - 3 | AE22: tier - 1 | AF22: =IF(AE22="?",$AF$6,AE22) -> tier - 1 | AI22: R1012 | AJ22: =IF(AI22="?","Unknown",AI22) -> R1012 | AS22: Id21 | AT22: 36.3 | AU22: 11.5 | AV22: No | AW22: No | AX22: Yes | AY22: Yes | AZ22: 2 | BA22: Myles | BB22: Diabetes | BC22: Obesity
A23: Id22 | B23: 32.2 | C23: 6.22 | D23: yes | E23: No | F23: No | G23: 2 | H23: yes | R23: Dec | S23: 1995 | U23: =SUBSTITUTE(R23,"?","Sep") -> Dec | V23: =IF(S23="?",ROUND(AVERAGEIF($S$5:$S$2347,"<>?"),0),S23) -> 1995 | Y23: yes | Z23: =IF(Y23="?",$Z$6,Y23) -> yes | AB23: tier - 3 | AC23: =IF(AB23="?",$AC$6,AB23) -> tier - 3 | AE23: tier - 1 | AF23: =IF(AE23="?",$AF$6,AE23) -> tier - 1 | AI23: R1013 | AJ23: =IF(AI23="?","Unknown",AI23) -> R1013 | AS23: Id22 | AT23: 32.2 | AU23: 6.22 | AV23: No | AW23: No | AX23: Yes | AY23: Yes | AZ23: 2 | BA23: Madelyn C | BB23: Prediabetes | BC23: Obesity
A24: Id23 | B24: 31.3 | C24: 11.38 | D24: No | E24: No | F24: No | G24: 3 | H24: yes | R24: Oct | S24: 2004 | U24: =SUBSTITUTE(R24,"?","Sep") -> Oct | V24: =IF(S24="?",ROUND(AVERAGEIF($S$5:$S$2347,"<>?"),0),S24) -> 2004 | Y24: yes | Z24: =IF(Y24="?",$Z$6,Y24) -> yes | AB24: tier - 3 | AC24: =IF(AB24="?",$AC$6,AB24) -> tier - 3 | AE24: tier - 3 | AF24: =IF(AE24="?",$AF$6,AE24) -> tier - 3 | AI24: R1011 | AJ24: =IF(AI24="?","Unknown",AI24) -> R1011 | AS24: Id23 | AT24: 31.3 | AU24: 11.38 | AV24: No | AW24: No | AX24: No | AY24: Yes | AZ24: 3 | BA24: Nicole | BB24: Diabetes | BC24: Obesity
A25: Id24 | B25: 41.8 | C25: 7.89 | D25: yes | E25: No | F25: No | G25: 2 | H25: yes | R25: Nov | S25: 2000 | U25: =SUBSTITUTE(R25,"?","Sep") -> Nov | V25: =IF(S25="?",ROUND(AVERAGEIF($S$5:$S$2347,"<>?"),0),S25) -> 2000 | Y25: yes | Z25: =IF(Y25="?",$Z$6,Y25) -> yes | AB25: tier - 3 | AC25: =IF(AB25="?",$AC$6,AB25) -> tier - 3 | AE25: tier - 3 | AF25: =IF(AE25="?",$AF$6,AE25) -> tier - 3 | AI25: R1013 | AJ25: =IF(AI25="?","Unknown",AI25) -> R1013 | AS25: Id24 | AT25: 41.8 | AU25: 7.89 | AV25: No | AW25: No | AX25: Yes | AY25: Yes | AZ25: 2 | BA25: Eric A. | BB25: Diabetes | BC25: Obesity
A26: Id25 | B26: 35.09 | C26: 4.38 | D26: yes | E26: No | F26: No | G26: 2 | H26: yes | R26: Nov | S26: 1993 | U26: =SUBSTITUTE(R26,"?","Sep") -> Nov | V26: =IF(S26="?",ROUND(AVERAGEIF($S$5:$S$2347,"<>?"),0),S26) -> 1993 | Y26: yes | Z26: =IF(Y26="?",$Z$6,Y26) -> yes | AB26: tier - 3 | AC26: =IF(AB26="?",$AC$6,AB26) -> tier - 3 | AE26: ? | AF26: =IF(AE26="?",$AF$6,AE26) -> tier - 2 | AI26: R1013 | AJ26: =IF(AI26="?","Unknown",AI26) -> R1013 | AS26: Id25 | AT26: 35.09 | AU26: 4.38 | AV26: No | AW26: No | AX26: Yes | AY26: Yes | AZ26: 2 | BA26: Emiliano I. | BB26: Normal | BC26: Obesity
A27: Id26 | B27: 33.88 | C27: 7.01 | D27: No | E27: No | F27: No | G27: 3 | H27: yes | R27: Oct | S27: 1994 | U27: =SUBSTITUTE(R27,"?","Sep") -> Oct | V27: =IF(S27="?",ROUND(AVERAGEIF($S$5:$S$2347,"<>?"),0),S27) -> 1994 | Y27: yes | Z27: =IF(Y27="?",$Z$6,Y27) -> yes | AB27: tier - 3 | AC27: =IF(AB27="?",$AC$6,AB27) -> tier - 3 | AE27: tier - 2 | AF27: =IF(AE27="?",$AF$6,AE27) -> tier - 2 | AI27: R1013 | AJ27: =IF(AI27="?","Unknown",AI27) -> R1013 | AS27: Id26 | AT27: 33.88 | AU27: 7.01 | AV27: No | AW27: No | AX27: No | AY27: Yes | AZ27: 3 | BA27: Adam | BB27: Diabetes | BC27: Obesity
A28: Id27 | B28: 30.875 | C28: 11.88 | D28: No | E28: No | F28: No | G28: No major surgery | H28: yes | R28: Oct | S28: 1995 | U28: =SUBSTITUTE(R28,"?","Sep") -> Oct | V28: =IF(S28="?",ROUND(AVERAGEIF($S$5:$S$2347,"<>?"),0),S28) -> 1995 | Y28: yes | Z28: =IF(Y28="?",$Z$6,Y28) -> yes | AB28: tier - 3 | AC28: =IF(AB28="?",$AC$6,AB28) -> tier - 3 | AE28: tier - 2 | AF28: =IF(AE28="?",$AF$6,AE28) -> tier - 2 | AI28: R1013 | AJ28: =IF(AI28="?","Unknown",AI28) -> R1013 | AS28: Id27 | AT28: 30.875 | AU28: 11.88 | AV28: No | AW28: No | AX28: No | AY28: Yes | AZ28: 0 | BA28: Zach | BB28: Diabetes | BC28: Obesity
A29: Id28 | B29: 36.86 | C29: 5.19 | D29: yes | E29: No | F29: Yes | G29: 1 | H29: yes | R29: Aug | S29: 2001 | U29: =SUBSTITUTE(R29,"?","Sep") -> Aug | V29: =IF(S29="?",ROUND(AVERAGEIF($S$5:$S$2347,"<>?"),0),S29) -> 2001 | Y29: yes | Z29: =IF(Y29="?",$Z$6,Y29) -> yes | AB29: tier - 3 | AC29: =IF(AB29="?",$AC$6,AB29) -> tier - 3 | AE29: tier - 1 | AF29: =IF(AE29="?",$AF$6,AE29) -> tier - 1 | AI29: R1013 | AJ29: =IF(AI29="?","Unknown",AI29) -> R1013 | AS29: Id28 | AT29: 36.86 | AU29: 5.19 | AV29: No | AW29: Yes | AX29: Yes | AY29: Yes | AZ29: 1 | BA29: Stephanie W. | BB29: Normal | BC29: Obesity
A30: Id29 | B30: 35.86 | C30: 6.74 | D30: yes | E30: No | F30: No | G30: 2 | H30: yes | R30: Nov | S30: 1994 | U30: =SUBSTITUTE(R30,"?","Sep") -> Nov | V30: =IF(S30="?",ROUND(AVERAGEIF($S$5:$S$2347,"<>?"),0),S30) -> 1994 | Y30: yes | Z30: =IF(Y30="?",$Z$6,Y30) -> yes | AB30: tier - 3 | AC30: =IF(AB30="?",$AC$6,AB30) -> tier - 3 | AE30: tier - 1 | AF30: =IF(AE30="?",$AF$6,AE30) -> tier - 1 | AI30: R1013 | AJ30: =IF(AI30="?","Unknown",AI30) -> R1013 | AS30: Id29 | AT30: 35.86 | AU30: 6.74 | AV30: No | AW30: No | AX30: Yes | AY30: Yes | AZ30: 2 | BA30: Stephen | BB30: Diabetes | BC30: Obesity
A31: Id30 | B31: 37.05 | C31: 8.44 | D31: No | E31: No | F31: No | G31: No major surgery | H31: yes | R31: Oct | S31: 2000 | U31: =SUBSTITUTE(R31,"?","Sep") -> Oct | V31: =IF(S31="?",ROUND(AVERAGEIF($S$5:$S$2347,"<>?"),0),S31) -> 2000 | Y31: yes | Z31: =IF(Y31="?",$Z$6,Y31) -> yes | AB31: tier - 3 | AC31: =IF(AB31="?",$AC$6,AB31) -> tier - 3 | AE31: tier - 1 | AF31: =IF(AE31="?",$AF$6,AE31) -> tier - 1 | AI31: R1013 | AJ31: =IF(AI31="?","Unknown",AI31) -> R1013 | AS31: Id30 | AT31: 37.05 | AU31: 8.44 | AV31: No | AW31: No | AX31: No | AY31: Yes | AZ31: 0 | BA31: Natalie | BB31: Diabetes | BC31: Obesity
A32: Id31 | B32: 43.89 | C32: 8.71 | D32: No | E32: No | F32: No | G32: No major surgery | H32: yes | R32: Aug | S32: 1999 | U32: =SUBSTITUTE(R32,"?","Sep") -> Aug | V32: =IF(S32="?",ROUND(AVERAGEIF($S$5:$S$2347,"<>?"),0),S32) -> 1999 | Y32: yes | Z32: =IF(Y32="?",$Z$6,Y32) -> yes | AB32: tier - 3 | AC32: =IF(AB32="?",$AC$6,AB32) -> tier - 3 | AE32: tier - 1 | AF32: =IF(AE32="?",$AF$6,AE32) -> tier - 1 | AI32: R1013 | AJ32: =IF(AI32="?","Unknown",AI32) -> R1013 | AS32: Id31 | AT32: 43.89 | AU32: 8.71 | AV32: No | AW32: No | AX32: No | AY32: Yes | AZ32: 0 | BA32: Nicole J. | BB32: Diabetes | BC32: Obesity
A33: Id32 | B33: 42.35 | C33: 5.08 | D33: yes | E33: No | F33: No | G33: No major surgery | H33: yes | R33: Oct | S33: 1995 | U33: =SUBSTITUTE(R33,"?","Sep") -> Oct | V33: =IF(S33="?",ROUND(AVERAGEIF($S$5:$S$2347,"<>?"),0),S33) -> 1995 | Y33: yes | Z33: =IF(Y33="?",$Z$6,Y33) -> yes | AB33: tier - 3 | AC33: =IF(AB33="?",$AC$6,AB33) -> tier - 3 | AE33: tier - 2 | AF33: =IF(AE33="?",$AF$6,AE33) -> tier - 2 | AI33: R1013 | AJ33: =IF(AI33="?","Unknown",AI33) -> R1013 | AS33: Id32 | AT33: 42.35 | AU33: 5.08 | AV33: No | AW33: No | AX33: Yes | AY33: Yes | AZ33: 0 | BA33: Jefferson D | BB33: Normal | BC33: Obesity
A34: Id33 | B34: 31.35 | C34: 6.86 | D34: No | E34: No | F34: No | G34: No major surgery | H34: yes | R34: Nov | S34: 1994 | U34: =SUBSTITUTE(R34,"?","Sep") -> Nov | V34: =IF(S34="?",ROUND(AVERAGEIF($S$5:$S$2347,"<>?"),0),S34) -> 1994 | Y34: yes | Z34: =IF(Y34="?",$Z$6,Y34) -> yes | AB34: tier - 3 | AC34: =IF(AB34="?",$AC$6,AB34) -> tier - 3 | AE34: tier - 2 | AF34: =IF(AE34="?",$AF$6,AE34) -> tier - 2 | AI34: R1013 | AJ34: =IF(AI34="?","Unknown",AI34) -> R1013 | AS34: Id33 | AT34: 31.35 | AU34: 6.86 | AV34: No | AW34: No | AX34: No | AY34: Yes | AZ34: 0 | BA34: Brendan D. | BB34: Diabetes | BC34: Obesity
A35: Id34 | B35: 47.6 | C35: 5.95 | D35: yes | E35: No | F35: No | G35: No major surgery | H35: yes | R35: Jul | S35: 2002 | U35: =SUBSTITUTE(R35,"?","Sep") -> Jul | V35: =IF(S35="?",ROUND(AVERAGEIF($S$5:$S$2347,"<>?"),0),S35) -> 2002 | Y35: yes | Z35: =IF(Y35="?",$Z$6,Y35) -> yes | AB35: tier - 3 | AC35: =IF(AB35="?",$AC$6,AB35) -> tier - 3 | AE35: tier - 2 | AF35: =IF(AE35="?",$AF$6,AE35) -> tier - 2 | AI35: R1013 | AJ35: =IF(AI35="?","Unknown",AI35) -> R1013 | AS35: Id34 | AT35: 47.6 | AU35: 5.95 | AV35: No | AW35: No | AX35: Yes | AY35: Yes | AZ35: 0 | BA35: Courtney | BB35: Prediabetes | BC35: Obesity
A36: Id35 | B36: 46.2 | C36: 6.09 | D36: No | E36: No | F36: Yes | G36: 1 | H36: yes | R36: Jul | S36: 2002 | U36: =SUBSTITUTE(R36,"?","Sep") -> Jul | V36: =IF(S36="?",ROUND(AVERAGEIF($S$5:$S$2347,"<>?"),0),S36) -> 2002 | Y36: yes | Z36: =IF(Y36="?",$Z$6,Y36) -> yes | AB36: tier - 3 | AC36: =IF(AB36="?",$AC$6,AB36) -> tier - 3 | AE36: tier - 2 | AF36: =IF(AE36="?",$AF$6,AE36) -> tier - 2 | AI36: R1012 | AJ36: =IF(AI36="?","Unknown",AI36) -> R1012 | AS36: Id35 | AT36: 46.2 | AU36: 6.09 | AV36: No | AW36: Yes | AX36: No | AY36: Yes | AZ36: 1 | BA36: Sydney L. | BB36: Prediabetes | BC36: Obesity
A37: Id36 | B37: 32.015 | C37: 11.75 | D37: No | E37: No | F37: No | G37: No major surgery | H37: yes | R37: Jun | S37: 1995 | U37: =SUBSTITUTE(R37,"?","Sep") -> Jun | V37: =IF(S37="?",ROUND(AVERAGEIF($S$5:$S$2347,"<>?"),0),S37) -> 1995 | Y37: yes | Z37: =IF(Y37="?",$Z$6,Y37) -> yes | AB37: tier - 3 | AC37: =IF(AB37="?",$AC$6,AB37) -> tier - 3 | AE37: tier - 1 | AF37: =IF(AE37="?",$AF$6,AE37) -> tier - 1 | AI37: R1013 | AJ37: =IF(AI37="?","Unknown",AI37) -> R1013 | AS37: Id36 | AT37: 32.015 | AU37: 11.75 | AV37: No | AW37: No | AX37: No | AY37: Yes | AZ37: 0 | BA37: Julien | BB37: Diabetes | BC37: Obesity
A38: Id37 | B38: 40.565 | C38: 7.37 | D38: No | E38: No | F38: No | G38: No major surgery | H38: yes | R38: Sep | S38: 1993 | U38: =SUBSTITUTE(R38,"?","Sep") -> Sep | V38: =IF(S38="?",ROUND(AVERAGEIF($S$5:$S$2347,"<>?"),0),S38) -> 1993 | Y38: yes | Z38: =IF(Y38="?",$Z$6,Y38) -> yes | AB38: tier - 3 | AC38: =IF(AB38="?",$AC$6,AB38) -> tier - 3 | AE38: tier - 2 | AF38: =IF(AE38="?",$AF$6,AE38) -> tier - 2 | AI38: R1013 | AJ38: =IF(AI38="?","Unknown",AI38) -> R1013 | AS38: Id37 | AT38: 40.565 | AU38: 7.37 | AV38: No | AW38: No | AX38: No | AY38: Yes | AZ38: 0 | BA38: Ryan M | BB38: Diabetes | BC38: Obesity
A39: Id38 | B39: 32.45 | C39: 11.91 | D39: No | E39: No | F39: No | G39: No major surgery | H39: yes | R39: Aug | S39: 2004 | U39: =SUBSTITUTE(R39,"?","Sep") -> Aug | V39: =IF(S39="?",ROUND(AVERAGEIF($S$5:$S$2347,"<>?"),0),S39) -> 2004 | Y39: yes | Z39: =IF(Y39="?",$Z$6,Y39) -> yes | AB39: tier - 3 | AC39: =IF(AB39="?",$AC$6,AB39) -> tier - 3 | AE39: tier - 1 | AF39: =IF(AE39="?",$AF$6,AE39) -> tier - 1 | AI39: R1013 | AJ39: =IF(AI39="?","Unknown",AI39) -> R1013 | AS39: Id38 | AT39: 32.45 | AU39: 11.91 | AV39: No | AW39: No | AX39: No | AY39: Yes | AZ39: 0 | BA39: Anna H. | BB39: Diabetes | BC39: Obesity
A40: Id39 | B40: 34.96 | C40: 6.52 | D40: No | E40: No | F40: No | G40: No major surgery | H40: yes | R40: Aug | S40: 1997 | U40: =SUBSTITUTE(R40,"?","Sep") -> Aug | V40: =IF(S40="?",ROUND(AVERAGEIF($S$5:$S$2347,"<>?"),0),S40) -> 1997 | Y40: yes | Z40: =IF(Y40="?",$Z$6,Y40) -> yes | AB40: tier - 3 | AC40: =IF(AB40="?",$AC$6,AB40) -> tier - 3 | AE40: tier - 2 | AF40: =IF(AE40="?",$AF$6,AE40) -> tier - 2 | AI40: R1013 | AJ40: =IF(AI40="?","Unknown",AI40) -> R1013 | AS40: Id39 | AT40: 34.96 | AU40: 6.52 | AV40: No | AW40: No | AX40: No | AY40: Yes | AZ40: 0 | BA40: Samantha | BB40: Diabetes | BC40: Obesity
A41: Id40 | B41: 35.5 | C41: 5.14 | D41: No | E41: No | F41: Yes | G41: 1 | H41: yes | R41: Dec | S41: 1998 | U41: =SUBSTITUTE(R41,"?","Sep") -> Dec | V41: =IF(S41="?",ROUND(AVERAGEIF($S$5:$S$2347,"<>?"),0),S41) -> 1998 | Y41: yes | Z41: =IF(Y41="?",$Z$6,Y41) -> yes | AB41: tier - 3 | AC41: =IF(AB41="?",$AC$6,AB41) -> tier - 3 | AE41: tier - 2 | AF41: =IF(AE41="?",$AF$6,AE41) -> tier - 2 | AI41: R1013 | AJ41: =IF(AI41="?","Unknown",AI41) -> R1013 | AS41: Id40 | AT41: 35.5 | AU41: 5.14 | AV41: No | AW41: Yes | AX41: No | AY41: Yes | AZ41: 1 | BA41: Robert | BB41: Normal | BC41: Obesity
A42: Id41 | B42: 52.58 | C42: 4.19 | D42: No | E42: yes | F42: No | G42: 1 | H42: yes | R42: Aug | S42: 2002 | U42: =SUBSTITUTE(R42,"?","Sep") -> Aug | V42: =IF(S42="?",ROUND(AVERAGEIF($S$5:$S$2347,"<>?"),0),S42) -> 2002 | Y42: yes | Z42: =IF(Y42="?",$Z$6,Y42) -> yes | AB42: tier - 3 | AC42: =IF(AB42="?",$AC$6,AB42) -> tier - 3 | AE42: tier - 1 | AF42: =IF(AE42="?",$AF$6,AE42) -> tier - 1 | AI42: R1013 | AJ42: =IF(AI42="?","Unknown",AI42) -> R1013 | AS42: Id41 | AT42: 52.58 | AU42: 4.19 | AV42: yes | AW42: No | AX42: No | AY42: Yes | AZ42: 1 | BA42: James R. | BB42: Normal | BC42: Obesity
A43: Id42 | B43: 35.2 | C43: 11.68 | D43: yes | E43: No | F43: No | G43: No major surgery | H43: yes | R43: Nov | S43: 2004 | U43: =SUBSTITUTE(R43,"?","Sep") -> Nov | V43: =IF(S43="?",ROUND(AVERAGEIF($S$5:$S$2347,"<>?"),0),S43) -> 2004 | Y43: yes | Z43: =IF(Y43="?",$Z$6,Y43) -> yes | AB43: tier - 3 | AC43: =IF(AB43="?",$AC$6,AB43) -> tier - 3 | AE43: tier - 3 | AF43: =IF(AE43="?",$AF$6,AE43) -> tier - 3 | AI43: R1013 | AJ43: =IF(AI43="?","Unknown",AI43) -> R1013 | AS43: Id42 | AT43: 35.2 | AU43: 11.68 | AV43: No | AW43: No | AX43: Yes | AY43: Yes | AZ43: 0 | BA43: Roseann | BB43: Diabetes | BC43: Obesity
A44: Id43 | B44: 38.06 | C44: 6.98 | D44: No | E44: No | F44: No | G44: No major surgery | H44: yes | R44: Jun | S44: 2004 | U44: =SUBSTITUTE(R44,"?","Sep") -> Jun | V44: =IF(S44="?",ROUND(AVERAGEIF($S$5:$S$2347,"<>?"),0),S44) -> 2004 | Y44: yes | Z44: =IF(Y44="?",$Z$6,Y44) -> yes | AB44: tier - 3 | AC44: =IF(AB44="?",$AC$6,AB44) -> tier - 3 | AE44: tier - 3 | AF44: =IF(AE44="?",$AF$6,AE44) -> tier - 3 | AI44: R1013 | AJ44: =IF(AI44="?","Unknown",AI44) -> R1013 | AS44: Id43 | AT44: 38.06 | AU44: 6.98 | AV44: No | AW44: No | AX44: No | AY44: Yes | AZ44: 0 | BA44: Nicole | BB44: Diabetes | BC44: Obesity
A45: Id44 | B45: 34.21 | C45: 8.34 | D45: No | E45: No | F45: No | G45: No major surgery | H45: yes | R45: Jul | S45: 2002 | U45: =SUBSTITUTE(R45,"?","Sep") -> Jul | V45: =IF(S45="?",ROUND(AVERAGEIF($S$5:$S$2347,"<>?"),0),S45) -> 2002 | Y45: yes | Z45: =IF(Y45="?",$Z$6,Y45) -> yes | AB45: tier - 3 | AC45: =IF(AB45="?",$AC$6,AB45) -> tier - 3 | AE45: tier - 2 | AF45: =IF(AE45="?",$AF$6,AE45) -> tier - 2 | AI45: R1013 | AJ45: =IF(AI45="?","Unknown",AI45) -> R1013 | AS45: Id44 | AT45: 34.21 | AU45: 8.34 | AV45: No | AW45: No | AX45: No | AY45: Yes | AZ45: 0 | BA45: Spencer | BB45: Diabetes | BC45: Obesity
A46: Id45 | B46: 38.94 | C46: 8.49 | D46: yes | E46: No | F46: No | G46: 1 | H46: yes | R46: Oct | S46: 2004 | U46: =SUBSTITUTE(R46,"?","Sep") -> Oct | V46: =IF(S46="?",ROUND(AVERAGEIF($S$5:$S$2347,"<>?"),0),S46) -> 2004 | Y46: yes | Z46: =IF(Y46="?",$Z$6,Y46) -> yes | AB46: tier - 3 | AC46: =IF(AB46="?",$AC$6,AB46) -> tier - 3 | AE46: tier - 3 | AF46: =IF(AE46="?",$AF$6,AE46) -> tier - 3 | AI46: R1013 | AJ46: =IF(AI46="?","Unknown",AI46) -> R1013 | AS46: Id45 | AT46: 38.94 | AU46: 8.49 | AV46: No | AW46: No | AX46: Yes | AY46: Yes | AZ46: 1 | BA46: Eric W | BB46: Diabetes | BC46: Obesity
A47: Id46 | B47: 30.21 | C47: 5.34 | D47: yes | E47: No | F47: No | G47: 1 | H47: yes | R47: Jun | S47: 2004 | U47: =SUBSTITUTE(R47,"?","Sep") -> Jun | V47: =IF(S47="?",ROUND(AVERAGEIF($S$5:$S$2347,"<>?"),0),S47) -> 2004 | Y47: yes | Z47: =IF(Y47="?",$Z$6,Y47) -> yes | AB47: tier - 3 | AC47: =IF(AB47="?",$AC$6,AB47) -> tier - 3 | AE47: tier - 1 | AF47: =IF(AE47="?",$AF$6,AE47) -> tier - 1 | AI47: R1013 | AJ47: =IF(AI47="?","Unknown",AI47) -> R1013 | AS47: Id46 | AT47: 30.21 | AU47: 5.34 | AV47: No | AW47: No | AX47: Yes | AY47: Yes | AZ47: 1 | BA47: Brianna L | BB47: Normal | BC47: Obesity
A48: Id47 | B48: 33.63 | C48: 4.43 | D48: yes | E48: No | F48: No | G48: 2 | H48: yes | R48: Nov | S48: 2004 | U48: =SUBSTITUTE(R48,"?","Sep") -> Nov | V48: =IF(S48="?",ROUND(AVERAGEIF($S$5:$S$2347,"<>?"),0),S48) -> 2004 | Y48: yes | Z48: =IF(Y48="?",$Z$6,Y48) -> yes | AB48: tier - 3 | AC48: =IF(AB48="?",$AC$6,AB48) -> tier - 3 | AE48: tier - 1 | AF48: =IF(AE48="?",$AF$6,AE48) -> tier - 1 | AI48: R1013 | AJ48: =IF(AI48="?","Unknown",AI48) -> R1013 | AS48: Id47 | AT48: 33.63 | AU48: 4.43 | AV48: No | AW48: No | AX48: Yes | AY48: Yes | AZ48: 2 | BA48: Thomas J. | BB48: Normal | BC48: Obesity
A49: Id48 | B49: 40.37 | C49: 4.47 | D49: No | E49: No | F49: No | G49: No major surgery | H49: yes | R49: Aug | S49: 2002 | U49: =SUBSTITUTE(R49,"?","Sep") -> Aug | V49: =IF(S49="?",ROUND(AVERAGEIF($S$5:$S$2347,"<>?"),0),S49) -> 2002 | Y49: yes | Z49: =IF(Y49="?",$Z$6,Y49) -> yes | AB49: tier - 3 | AC49: =IF(AB49="?",$AC$6,AB49) -> tier - 3 | AE49: tier - 1 | AF49: =IF(AE49="?",$AF$6,AE49) -> tier - 1 | AI49: R1013 | AJ49: =IF(AI49="?","Unknown",AI49) -> R1013 | AS49: Id48 | AT49: 40.37 | AU49: 4.47 | AV49: No | AW49: No | AX49: No | AY49: Yes | AZ49: 0 | BA49: Melissa L | BB49: Normal | BC49: Obesity
A50: Id49 | B50: 53.09 | C50: 4.82 | D50: yes | E50: No | F50: No | G50: 2 | H50: yes | R50: Nov | S50: 2004 | U50: =SUBSTITUTE(R50,"?","Sep") -> Nov | V50: =IF(S50="?",ROUND(AVERAGEIF($S$5:$S$2347,"<>?"),0),S50) -> 2004 | Y50: yes | Z50: =IF(Y50="?",$Z$6,Y50) -> yes | AB50: tier - 3 | AC50: =IF(AB50="?",$AC$6,AB50) -> tier - 3 | AE50: tier - 3 | AF50: =IF(AE50="?",$AF$6,AE50) -> tier - 3 | AI50: R1013 | AJ50: =IF(AI50="?","Unknown",AI50) -> R1013 | AS50: Id49 | AT50: 53.09 | AU50: 4.82 | AV50: No | AW50: No | AX50: Yes | AY50: Yes | AZ50: 2 | BA50: Flavio | BB50: Normal | BC50: Obesity
A51: Id50 | B51: 31.79 | C51: 5.51 | D51: yes | E51: No | F51: No | G51: 2 | H51: yes | R51: Oct | S51: 2004 | U51: =SUBSTITUTE(R51,"?","Sep") -> Oct | V51: =IF(S51="?",ROUND(AVERAGEIF($S$5:$S$2347,"<>?"),0),S51) -> 2004 | Y51: yes | Z51: =IF(Y51="?",$Z$6,Y51) -> yes | AB51: tier - 3 | AC51: =IF(AB51="?",$AC$6,AB51) -> tier - 3 | AE51: tier - 3 | AF51: =IF(AE51="?",$AF$6,AE51) -> tier - 3 | AI51: R1013 | AJ51: =IF(AI51="?","Unknown",AI51) -> R1013 | AS51: Id50 | AT51: 31.79 | AU51: 5.51 | AV51: No | AW51: No | AX51: Yes | AY51: Yes | AZ51: 2 | BA51: Ryan | BB51: Normal | BC51: Obesity
A52: Id51 | B52: 41.895 | C52: 10.87 | D52: yes | E52: No | F52: No | G52: 1 | H52: yes | R52: Nov | S52: 2004 | U52: =SUBSTITUTE(R52,"?","Sep") -> Nov | V52: =IF(S52="?",ROUND(AVERAGEIF($S$5:$S$2347,"<>?"),0),S52) -> 2004 | Y52: yes | Z52: =IF(Y52="?",$Z$6,Y52) -> yes | AB52: tier - 3 | AC52: =IF(AB52="?",$AC$6,AB52) -> tier - 3 | AE52: tier - 3 | AF52: =IF(AE52="?",$AF$6,AE52) -> tier - 3 | AI52: R1013 | AJ52: =IF(AI52="?","Unknown",AI52) -> R1013 | AS52: Id51 | AT52: 41.895 | AU52: 10.87 | AV52: No | AW52: No | AX52: Yes | AY52: Yes | AZ52: 1 | BA52: Anthony J. | BB52: Diabetes | BC52: Obesity
A53: Id52 | B53: 31.16 | C53: 9.34 | D53: No | E53: No | F53: No | G53: No major surgery | H53: yes | R53: Oct | S53: 2001 | U53: =SUBSTITUTE(R53,"?","Sep") -> Oct | V53: =IF(S53="?",ROUND(AVERAGEIF($S$5:$S$2347,"<>?"),0),S53) -> 2001 | Y53: yes | Z53: =IF(Y53="?",$Z$6,Y53) -> yes | AB53: tier - 3 | AC53: =IF(AB53="?",$AC$6,AB53) -> tier - 3 | AE53: tier - 1 | AF53: =IF(AE53="?",$AF$6,AE53) -> tier - 1 | AI53: R1013 | AJ53: =IF(AI53="?","Unknown",AI53) -> R1013 | AS53: Id52 | AT53: 31.16 | AU53: 9.34 | AV53: No | AW53: No | AX53: No | AY53: Yes | AZ53: 0 | BA53: Alex | BB53: Diabetes | BC53: Obesity
A54: Id53 | B54: 34.105 | C54: 5.03 | D54: yes | E54: No | F54: Yes | G54: 1 | H54: yes | R54: Sep | S54: 2004 | U54: =SUBSTITUTE(R54,"?","Sep") -> Sep | V54: =IF(S54="?",ROUND(AVERAGEIF($S$5:$S$2347,"<>?"),0),S54) -> 2004 | Y54: yes | Z54: =IF(Y54="?",$Z$6,Y54) -> yes | AB54: tier - 3 | AC54: =IF(AB54="?",$AC$6,AB54) -> tier - 3 | AE54: tier - 1 | AF54: =IF(AE54="?",$AF$6,AE54) -> tier - 1 | AI54: R1013 | AJ54: =IF(AI54="?","Unknown",AI54) -> R1013 | AS54: Id53 | AT54: 34.105 | AU54: 5.03 | AV54: No | AW54: Yes | AX54: Yes | AY54: Yes | AZ54: 1 | BA54: David | BB54: Normal | BC54: Obesity
A55: Id54 | B55: 51.93 | C55: 11.05 | D55: No | E55: No | F55: No | G55: No major surgery | H55: yes | R55: Oct | S55: 2002 | U55: =SUBSTITUTE(R55,"?","Sep") -> Oct | V55: =IF(S55="?",ROUND(AVERAGEIF($S$5:$S$2347,"<>?"),0),S55) -> 2002 | Y55: yes | Z55: =IF(Y55="?",$Z$6,Y55) -> yes | AB55: tier - 3 | AC55: =IF(AB55="?",$AC$6,AB55) -> tier - 3 | AE55: tier - 1 | AF55: =IF(AE55="?",$AF$6,AE55) -> tier - 1 | AI55: R1011 | AJ55: =IF(AI55="?","Unknown",AI55) -> R1011 | AS55: Id54 | AT55: 51.93 | AU55: 11.05 | AV55: No | AW55: No | AX55: No | AY55: Yes | AZ55: 0 | BA55: Andrew B | BB55: Diabetes | BC55: Obesity
A56: Id55 | B56: 38.95 | C56: 11.95 | D56: No | E56: No | F56: No | G56: No major surgery | H56: yes | R56: Jun | S56: 2004 | U56: =SUBSTITUTE(R56,"?","Sep") -> Jun | V56: =IF(S56="?",ROUND(AVERAGEIF($S$5:$S$2347,"<>?"),0),S56) -> 2004 | Y56: yes | Z56: =IF(Y56="?",$Z$6,Y56) -> yes | AB56: tier - 3 | AC56: =IF(AB56="?",$AC$6,AB56) -> tier - 3 | AE56: tier - 2 | AF56: =IF(AE56="?",$AF$6,AE56) -> tier - 2 | AI56: R1013 | AJ56: =IF(AI56="?","Unknown",AI56) -> R1013 | AS56: Id55 | AT56: 38.95 | AU56: 11.95 | AV56: No | AW56: No | AX56: No | AY56: Yes | AZ56: 0 | BA56: Dara E | BB56: Diabetes | BC56: Obesity
A57: Id56 | B57: 36.63 | C57: 7.72 | D57: yes | E57: No | F57: No | G57: 1 | H57: yes | R57: Jun | S57: 2003 | U57: =SUBSTITUTE(R57,"?","Sep") -> Jun | V57: =IF(S57="?",ROUND(AVERAGEIF($S$5:$S$2347,"<>?"),0),S57) -> 2003 | Y57: yes | Z57: =IF(Y57="?",$Z$6,Y57) -> yes | AB57: tier - 3 | AC57: =IF(AB57="?",$AC$6,AB57) -> tier - 3 | AE57: tier - 1 | AF57: =IF(AE57="?",$AF$6,AE57) -> tier - 1 | AI57: R1012 | AJ57: =IF(AI57="?","Unknown",AI57) -> R1012 | AS57: Id56 | AT57: 36.63 | AU57: 7.72 | AV57: No | AW57: No | AX57: Yes | AY57: Yes | AZ57: 1 | BA57: Inna | BB57: Diabetes | BC57: Obesity
A58: Id57 | B58: 34.2 | C58: 5.75 | D58: No | E58: No | F58: No | G58: 2 | H58: yes | R58: Jul | S58: 2004 | U58: =SUBSTITUTE(R58,"?","Sep") -> Jul | V58: =IF(S58="?",ROUND(AVERAGEIF($S$5:$S$2347,"<>?"),0),S58) -> 2004 | Y58: yes | Z58: =IF(Y58="?",$Z$6,Y58) -> yes | AB58: tier - 3 | AC58: =IF(AB58="?",$AC$6,AB58) -> tier - 3 | AE58: tier - 3 | AF58: =IF(AE58="?",$AF$6,AE58) -> tier - 3 | AI58: R1013 | AJ58: =IF(AI58="?","Unknown",AI58) -> R1013 | AS58: Id57 | AT58: 34.2 | AU58: 5.75 | AV58: No | AW58: No | AX58: No | AY58: Yes | AZ58: 2 | BA58: Ari | BB58: Prediabetes | BC58: Obesity
A59: Id58 | B59: 50.63 | C59: 11.89 | D59: No | E59: No | F59: No | G59: No major surgery | H59: yes | R59: Jul | S59: 1994 | U59: =SUBSTITUTE(R59,"?","Sep") -> Jul | V59: =IF(S59="?",ROUND(AVERAGEIF($S$5:$S$2347,"<>?"),0),S59) -> 1994 | Y59: yes | Z59: =IF(Y59="?",$Z$6,Y59) -> yes | AB59: tier - 3 | AC59: =IF(AB59="?",$AC$6,AB59) -> tier - 3 | AE59: tier - 2 | AF59: =IF(AE59="?",$AF$6,AE59) -> tier - 2 | AI59: R1013 | AJ59: =IF(AI59="?","Unknown",AI59) -> R1013 | AS59: Id58 | AT59: 50.63 | AU59: 11.89 | AV59: No | AW59: No | AX59: No | AY59: Yes | AZ59: 0 | BA59: Lindsey | BB59: Diabetes | BC59: Obesity
A60: Id59 | B60: 36.48 | C60: 6.2 | D60: No | E60: No | F60: No | G60: No major surgery | H60: yes | R60: Nov | S60: 2004 | U60: =SUBSTITUTE(R60,"?","Sep") -> Nov | V60: =IF(S60="?",ROUND(AVERAGEIF($S$5:$S$2347,"<>?"),0),S60) -> 2004 | Y60: yes | Z60: =IF(Y60="?",$Z$6,Y60) -> yes | AB60: tier - 2 | AC60: =IF(AB60="?",$AC$6,AB60) -> tier - 2 | AE60: tier - 2 | AF60: =IF(AE60="?",$AF$6,AE60) -> tier - 2 | AI60: R1013 | AJ60: =IF(AI60="?","Unknown",AI60) -> R1013 | AS60: Id59 | AT60: 36.48 | AU60: 6.2 | AV60: No | AW60: No | AX60: No | AY60: Yes | AZ60: 0 | BA60: Kenny | BB60: Prediabetes | BC60: Obesity
A61: Id60 | B61: 54.82 | C61: 10.61 | D61: No | E61: No | F61: No | G61: No major surgery | H61: yes | R61: Jun | S61: 2002 | U61: =SUBSTITUTE(R61,"?","Sep") -> Jun | V61: =IF(S61="?",ROUND(AVERAGEIF($S$5:$S$2347,"<>?"),0),S61) -> 2002 | Y61: yes | Z61: =IF(Y61="?",$Z$6,Y61) -> yes | AB61: tier - 2 | AC61: =IF(AB61="?",$AC$6,AB61) -> tier - 2 | AE61: tier - 1 | AF61: =IF(AE61="?",$AF$6,AE61) -> tier - 1 | AI61: R1012 | AJ61: =IF(AI61="?","Unknown",AI61) -> R1012 | AS61: Id60 | AT61: 54.82 | AU61: 10.61 | AV61: No | AW61: No | AX61: No | AY61: Yes | AZ61: 0 | BA61: Louise | BB61: Diabetes | BC61: Obesity
A62: Id61 | B62: 38.06 | C62: 6.04 | D62: No | E62: No | F62: Yes | G62: 1 | H62: yes | R62: Nov | S62: 2001 | U62: =SUBSTITUTE(R62,"?","Sep") -> Nov | V62: =IF(S62="?",ROUND(AVERAGEIF($S$5:$S$2347,"<>?"),0),S62) -> 2001 | Y62: yes | Z62: =IF(Y62="?",$Z$6,Y62) -> yes | AB62: tier - 2 | AC62: =IF(AB62="?",$AC$6,AB62) -> tier - 2 | AE62: tier - 2 | AF62: =IF(AE62="?",$AF$6,AE62) -> tier - 2 | AI62: R1013 | AJ62: =IF(AI62="?","Unknown",AI62) -> R1013 | AS62: Id61 | AT62: 38.06 | AU62: 6.04 | AV62: No | AW62: Yes | AX62: No | AY62: Yes | AZ62: 1 | BA62: Cameron | BB62: Prediabetes | BC62: Obesity
A63: Id62 | B63: 51.48 | C63: 9.33 | D63: yes | E63: No | F63: No | G63: No major surgery | H63: yes | R63: Aug | S63: 1996 | U63: =SUBSTITUTE(R63,"?","Sep") -> Aug | V63: =IF(S63="?",ROUND(AVERAGEIF($S$5:$S$2347,"<>?"),0),S63) -> 1996 | Y63: yes | Z63: =IF(Y63="?",$Z$6,Y63) -> yes | AB63: tier - 2 | AC63: =IF(AB63="?",$AC$6,AB63) -> tier - 2 | AE63: tier - 1 | AF63: =IF(AE63="?",$AF$6,AE63) -> tier - 1 | AI63: R1013 | AJ63: =IF(AI63="?","Unknown",AI63) -> R1013 | AS63: Id62 | AT63: 51.48 | AU63: 9.33 | AV63: No | AW63: No | AX63: Yes | AY63: Yes | AZ63: 0 | BA63: Katie T. | BB63: Diabetes | BC63: Obesity
A64: Id63 | B64: 52.06 | C64: 11.47 | D64: No | E64: No | F64: No | G64: No major surgery | H64: yes | R64: Jun | S64: 1997 | U64: =SUBSTITUTE(R64,"?","Sep") -> Jun | V64: =IF(S64="?",ROUND(AVERAGEIF($S$5:$S$2347,"<>?"),0),S64) -> 1997 | Y64: yes | Z64: =IF(Y64="?",$Z$6,Y64) -> yes | AB64: tier - 2 | AC64: =IF(AB64="?",$AC$6,AB64) -> tier - 2 | AE64: tier - 3 | AF64: =IF(AE64="?",$AF$6,AE64) -> tier - 3 | AI64: R1013 | AJ64: =IF(AI64="?","Unknown",AI64) -> R1013 | AS64: Id63 | AT64: 52.06 | AU64: 11.47 | AV64: No | AW64: No | AX64: No | AY64: Yes | AZ64: 0 | BA64: Casey | BB64: Diabetes | BC64: Obesity
A65: Id64 | B65: 30.685 | C65: 7.02 | D65: yes | E65: No | F65: No | G65: No major surgery | H65: yes | R65: Aug | S65: 2002 | U65: =SUBSTITUTE(R65,"?","Sep") -> Aug | V65: =IF(S65="?",ROUND(AVERAGEIF($S$5:$S$2347,"<>?"),0),S65) -> 2002 | Y65: yes | Z65: =IF(Y65="?",$Z$6,Y65) -> yes | AB65: tier - 2 | AC65: =IF(AB65="?",$AC$6,AB65) -> tier - 2 | AE65: tier - 3 | AF65: =IF(AE65="?",$AF$6,AE65) -> tier - 3 | AI65: R1013 | AJ65: =IF(AI65="?","Unknown",AI65) -> R1013 | AS65: Id64 | AT65: 30.685 | AU65: 7.02 | AV65: No | AW65: No | AX65: Yes | AY65: Yes | AZ65: 0 | BA65: David | BB65: Diabetes | BC65: Obesity
A66: Id65 | B66: 36.08 | C66: 8.8 | D66: yes | E66: No | F66: No | G66: 1 | H66: yes | R66: Jun | S66: 1999 | U66: =SUBSTITUTE(R66,"?","Sep") -> Jun | V66: =IF(S66="?",ROUND(AVERAGEIF($S$5:$S$2347,"<>?"),0),S66) -> 1999 | Y66: yes | Z66: =IF(Y66="?",$Z$6,Y66) -> yes | AB66: tier - 2 | AC66: =IF(AB66="?",$AC$6,AB66) -> tier - 2 | AE66: tier - 1 | AF66: =IF(AE66="?",$AF$6,AE66) -> tier - 1 | AI66: R1012 | AJ66: =IF(AI66="?","Unknown",AI66) -> R1012 | AS66: Id65 | AT66: 36.08 | AU66: 8.8 | AV66: No | AW66: No | AX66: Yes | AY66: Yes | AZ66: 1 | BA66: Bryson C. | BB66: Diabetes | BC66: Obesity
A67: Id66 | B67: 54.99 | C67: 8.68 | D67: No | E67: No | F67: No | G67: 2 | H67: yes | R67: Oct | S67: 1992 | U67: =SUBSTITUTE(R67,"?","Sep") -> Oct | V67: =IF(S67="?",ROUND(AVERAGEIF($S$5:$S$2347,"<>?"),0),S67) -> 1992 | Y67: yes | Z67: =IF(Y67="?",$Z$6,Y67) -> yes | AB67: tier - 2 | AC67: =IF(AB67="?",$AC$6,AB67) -> tier - 2 | AE67: tier - 3 | AF67: =IF(AE67="?",$AF$6,AE67) -> tier - 3 | AI67: R1013 | AJ67: =IF(AI67="?","Unknown",AI67) -> R1013 | AS67: Id66 | AT67: 54.99 | AU67: 8.68 | AV67: No | AW67: No | AX67: No | AY67: Yes | AZ67: 2 | BA67: Megan | BB67: Diabetes | BC67: Obesity
A68: Id67 | B68: 35.97 | C68: 6.12 | D68: No | E68: No | F68: Yes | G68: 1 | H68: yes | R68: Jun | S68: 2004 | U68: =SUBSTITUTE(R68,"?","Sep") -> Jun | V68: =IF(S68="?",ROUND(AVERAGEIF($S$5:$S$2347,"<>?"),0),S68) -> 2004 | Y68: yes | Z68: =IF(Y68="?",$Z$6,Y68) -> yes | AB68: tier - 2 | AC68: =IF(AB68="?",$AC$6,AB68) -> tier - 2 | AE68: tier - 2 | AF68: =IF(AE68="?",$AF$6,AE68) -> tier - 2 | AI68: R1013 | AJ68: =IF(AI68="?","Unknown",AI68) -> R1013 | AS68: Id67 | AT68: 35.97 | AU68: 6.12 | AV68: No | AW68: Yes | AX68: No | AY68: Yes | AZ68: 1 | BA68: Daniel | BB68: Prediabetes | BC68: Obesity
A69: Id68 | B69: 45.54 | C69: 5.4 | D69: yes | E69: No | F69: Yes | G69: 1 | H69: yes | R69: Nov | S69: 1996 | U69: =SUBSTITUTE(R69,"?","Sep") -> Nov | V69: =IF(S69="?",ROUND(AVERAGEIF($S$5:$S$2347,"<>?"),0),S69) -> 1996 | Y69: yes | Z69: =IF(Y69="?",$Z$6,Y69) -> yes | AB69: tier - 2 | AC69: =IF(AB69="?",$AC$6,AB69) -> tier - 2 | AE69: tier - 1 | AF69: =IF(AE69="?",$AF$6,AE69) -> tier - 1 | AI69: R1012 | AJ69: =IF(AI69="?","Unknown",AI69) -> R1012 | AS69: Id68 | AT69: 45.54 | AU69: 5.4 | AV69: No | AW69: Yes | AX69: Yes | AY69: Yes | AZ69: 1 | BA69: Steven M. | BB69: Normal | BC69: Obesity
A70: Id69 | B70: 35.53 | C70: 4.36 | D70: yes | E70: No | F70: No | G70: No major surgery | H70: yes | R70: Jul | S70: 2004 | U70: =SUBSTITUTE(R70,"?","Sep") -> Jul | V70: =IF(S70="?",ROUND(AVERAGEIF($S$5:$S$2347,"<>?"),0),S70) -> 2004 | Y70: yes | Z70: =IF(Y70="?",$Z$6,Y70) -> yes | AB70: tier - 2 | AC70: =IF(AB70="?",$AC$6,AB70) -> tier - 2 | AE70: tier - 3 | AF70: =IF(AE70="?",$AF$6,AE70) -> tier - 3 | AI70: R1013 | AJ70: =IF(AI70="?","Unknown",AI70) -> R1013 | AS70: Id69 | AT70: 35.53 | AU70: 4.36 | AV70: No | AW70: No | AX70: Yes | AY70: Yes | AZ70: 0 | BA70: Jenna L. | BB70: Normal | BC70: Obesity
A71: Id70 | B71: 30.8 | C71: 9.77 | D71: No | E71: No | F71: No | G71: No major surgery | H71: yes | R71: Oct | S71: 2004 | U71: =SUBSTITUTE(R71,"?","Sep") -> Oct | V71: =IF(S71="?",ROUND(AVERAGEIF($S$5:$S$2347,"<>?"),0),S71) -> 2004 | Y71: yes | Z71: =IF(Y71="?",$Z$6,Y71) -> yes | AB71: tier - 2 | AC71: =IF(AB71="?",$AC$6,AB71) -> tier - 2 | AE71: tier - 3 | AF71: =IF(AE71="?",$AF$6,AE71) -> tier - 3 | AI71: R1012 | AJ71: =IF(AI71="?","Unknown",AI71) -> R1012 | AS71: Id70 | AT71: 30.8 | AU71: 9.77 | AV71: No | AW71: No | AX71: No | AY71: Yes | AZ71: 0 | BA71: Freeman | BB71: Diabetes | BC71: Obesity
A72: Id71 | B72: 38.39 | C72: 4.25 | D72: No | E72: No | F72: No | G72: 1 | H72: yes | R72: Jul | S72: 1998 | U72: =SUBSTITUTE(R72,"?","Sep") -> Jul | V72: =IF(S72="?",ROUND(AVERAGEIF($S$5:$S$2347,"<>?"),0),S72) -> 1998 | Y72: yes | Z72: =IF(Y72="?",$Z$6,Y72) -> yes | AB72: tier - 2 | AC72: =IF(AB72="?",$AC$6,AB72) -> tier - 2 | AE72: tier - 1 | AF72: =IF(AE72="?",$AF$6,AE72) -> tier - 1 | AI72: R1013 | AJ72: =IF(AI72="?","Unknown",AI72) -> R1013 | AS72: Id71 | AT72: 38.39 | AU72: 4.25 | AV72: No | AW72: No | AX72: No | AY72: Yes | AZ72: 1 | BA72: Jeff | BB72: Normal | BC72: Obesity
A73: Id72 | B73: 32.3 | C73: 4.76 | D73: No | E73: No | F73: No | G73: 2 | H73: yes | R73: Dec | S73: 2002 | U73: =SUBSTITUTE(R73,"?","Sep") -> Dec | V73: =IF(S73="?",ROUND(AVERAGEIF($S$5:$S$2347,"<>?"),0),S73) -> 2002 | Y73: yes | Z73: =IF(Y73="?",$Z$6,Y73) -> yes | AB73: tier - 2 | AC73: =IF(AB73="?",$AC$6,AB73) -> tier - 2 | AE73: tier - 3 | AF73: =IF(AE73="?",$AF$6,AE73) -> tier - 3 | AI73: R1013 | AJ73: =IF(AI73="?","Unknown",AI73) -> R1013 | AS73: Id72 | AT73: 32.3 | AU73: 4.76 | AV73: No | AW73: No | AX73: No | AY73: Yes | AZ73: 2 | BA73: Elenilton V. Sr. | BB73: Normal | BC73: Obesity
A74: Id73 | B74: 48.8 | C74: 6.22 | D74: yes | E74: No | F74: No | G74: 2 | H74: yes | R74: Oct | S74: 1998 | U74: =SUBSTITUTE(R74,"?","Sep") -> Oct | V74: =IF(S74="?",ROUND(AVERAGEIF($S$5:$S$2347,"<>?"),0),S74) -> 1998 | Y74: yes | Z74: =IF(Y74="?",$Z$6,Y74) -> yes | AB74: tier - 2 | AC74: =IF(AB74="?",$AC$6,AB74) -> tier - 2 | AE74: tier - 1 | AF74: =IF(AE74="?",$AF$6,AE74) -> tier - 1 | AI74: R1012 | AJ74: =IF(AI74="?","Unknown",AI74) -> R1012 | AS74: Id73 | AT74: 48.8 | AU74: 6.22 | AV74: No | AW74: No | AX74: Yes | AY74: Yes | AZ74: 2 | BA74: Maurya | BB74: Prediabetes | BC74: Obesity
A75: Id74 | B75: 45.5 | C75: 7.96 | D75: No | E75: No | F75: No | G75: No major surgery | H75: yes | R75: Jul | S75: 2002 | U75: =SUBSTITUTE(R75,"?","Sep") -> Jul | V75: =IF(S75="?",ROUND(AVERAGEIF($S$5:$S$2347,"<>?"),0),S75) -> 2002 | Y75: yes | Z75: =IF(Y75="?",$Z$6,Y75) -> yes | AB75: tier - 2 | AC75: =IF(AB75="?",$AC$6,AB75) -> tier - 2 | AE75: tier - 1 | AF75: =IF(AE75="?",$AF$6,AE75) -> tier - 1 | AI75: R1013 | AJ75: =IF(AI75="?","Unknown",AI75) -> R1013 | AS75: Id74 | AT75: 45.5 | AU75: 7.96 | AV75: No | AW75: No | AX75: No | AY75: Yes | AZ75: 0 | BA75: Samantha C | BB75: Diabetes | BC75: Obesity
A76: Id75 | B76: 53.61 | C76: 10.92 | D76: yes | E76: No | F76: No | G76: 1 | H76: yes | R76: Aug | S76: 2003 | U76: =SUBSTITUTE(R76,"?","Sep") -> Aug | V76: =IF(S76="?",ROUND(AVERAGEIF($S$5:$S$2347,"<>?"),0),S76) -> 2003 | Y76: yes | Z76: =IF(Y76="?",$Z$6,Y76) -> yes | AB76: tier - 2 | AC76: =IF(AB76="?",$AC$6,AB76) -> tier - 2 | AE76: tier - 1 | AF76: =IF(AE76="?",$AF$6,AE76) -> tier - 1 | AI76: R1011 | AJ76: =IF(AI76="?","Unknown",AI76) -> R1011 | AS76: Id75 | AT76: 53.61 | AU76: 10.92 | AV76: No | AW76: No | AX76: Yes | AY76: Yes | AZ76: 1 | BA76: Bethany A | BB76: Diabetes | BC76: Obesity
A77: Id76 | B77: 36.19 | C77: 11.51 | D77: yes | E77: No | F77: No | G77: 1 | H77: yes | R77: Sep | S77: 2003 | U77: =SUBSTITUTE(R77,"?","Sep") -> Sep | V77: =IF(S77="?",ROUND(AVERAGEIF($S$5:$S$2347,"<>?"),0),S77) -> 2003 | Y77: yes | Z77: =IF(Y77="?",$Z$6,Y77) -> yes | AB77: tier - 2 | AC77: =IF(AB77="?",$AC$6,AB77) -> tier - 2 | AE77: tier - 2 | AF77: =IF(AE77="?",$AF$6,AE77) -> tier - 2 | AI77: R1011 | AJ77: =IF(AI77="?","Unknown",AI77) -> R1011 | AS77: Id76 | AT77: 36.19 | AU77: 11.51 | AV77: No | AW77: No | AX77: Yes | AY77: Yes | AZ77: 1 | BA77: Yves | BB77: Diabetes | BC77: Obesity
A78: Id77 | B78: 34.6 | C78: 5.99 | D78: yes | E78: No | F78: No | G78: No major surgery | H78: yes | R78: Sep | S78: 2003 | U78: =SUBSTITUTE(R78,"?","Sep") -> Sep | V78: =IF(S78="?",ROUND(AVERAGEIF($S$5:$S$2347,"<>?"),0),S78) -> 2003 | Y78: yes | Z78: =IF(Y78="?",$Z$6,Y78) -> yes | AB78: tier - 2 | AC78: =IF(AB78="?",$AC$6,AB78) -> tier - 2 | AE78: tier - 1 | AF78: =IF(AE78="?",$AF$6,AE78) -> tier - 1 | AI78: R1011 | AJ78: =IF(AI78="?","Unknown",AI78) -> R1011 | AS78: Id77 | AT78: 34.6 | AU78: 5.99 | AV78: No | AW78: No | AX78: Yes | AY78: Yes | AZ78: 0 | BA78: Danielle | BB78: Prediabetes | BC78: Obesity
A79: Id78 | B79: 54.12 | C79: 11.57 | D79: No | E79: No | F79: No | G79: No major surgery | H79: yes | R79: Sep | S79: 2003 | U79: =SUBSTITUTE(R79,"?","Sep") -> Sep | V79: =IF(S79="?",ROUND(AVERAGEIF($S$5:$S$2347,"<>?"),0),S79) -> 2003 | Y79: yes | Z79: =IF(Y79="?",$Z$6,Y79) -> yes | AB79: tier - 2 | AC79: =IF(AB79="?",$AC$6,AB79) -> tier - 2 | AE79: tier - 2 | AF79: =IF(AE79="?",$AF$6,AE79) -> tier - 2 | AI79: R1011 | AJ79: =IF(AI79="?","Unknown",AI79) -> R1011 | AS79: Id78 | AT79: 54.12 | AU79: 11.57 | AV79: No | AW79: No | AX79: No | AY79: Yes | AZ79: 0 | BA79: Julia | BB79: Diabetes | BC79: Obesity
A80: Id79 | B80: 48.82 | C80: 6.67 | D80: yes | E80: No | F80: No | G80: No major surgery | H80: yes | R80: Nov | S80: 1997 | U80: =SUBSTITUTE(R80,"?","Sep") -> Nov | V80: =IF(S80="?",ROUND(AVERAGEIF($S$5:$S$2347,"<>?"),0),S80) -> 1997 | Y80: yes | Z80: =IF(Y80="?",$Z$6,Y80) -> yes | AB80: tier - 2 | AC80: =IF(AB80="?",$AC$6,AB80) -> tier - 2 | AE80: tier - 2 | AF80: =IF(AE80="?",$AF$6,AE80) -> tier - 2 | AI80: R1013 | AJ80: =IF(AI80="?","Unknown",AI80) -> R1013 | AS80: Id79 | AT80: 48.82 | AU80: 6.67 | AV80: No | AW80: No | AX80: Yes | AY80: Yes | AZ80: 0 | BA80: Joshua | BB80: Diabetes | BC80: Obesity
A81: Id80 | B81: 51.01 | C81: 9.2 | D81: No | E81: No | F81: No | G81: No major surgery | H81: yes | R81: Dec | S81: 2003 | U81: =SUBSTITUTE(R81,"?","Sep") -> Dec | V81: =IF(S81="?",ROUND(AVERAGEIF($S$5:$S$2347,"<>?"),0),S81) -> 2003 | Y81: yes | Z81: =IF(Y81="?",$Z$6,Y81) -> yes | AB81: tier - 2 | AC81: =IF(AB81="?",$AC$6,AB81) -> tier - 2 | AE81: tier - 1 | AF81: =IF(AE81="?",$AF$6,AE81) -> tier - 1 | AI81: R1011 | AJ81: =IF(AI81="?","Unknown",AI81) -> R1011 | AS81: Id80 | AT81: 51.01 | AU81: 9.2 | AV81: No | AW81: No | AX81: No | AY81: Yes | AZ81: 0 | BA81: Jennifer | BB81: Diabetes | BC81: Obesity
A82: Id81 | B82: 45.65 | C82: 5.11 | D82: yes | E82: No | F82: No | G82: 1 | H82: yes | R82: Oct | S82: 2003 | U82: =SUBSTITUTE(R82,"?","Sep") -> Oct | V82: =IF(S82="?",ROUND(AVERAGEIF($S$5:$S$2347,"<>?"),0),S82) -> 2003 | Y82: yes | Z82: =IF(Y82="?",$Z$6,Y82) -> yes | AB82: tier - 2 | AC82: =IF(AB82="?",$AC$6,AB82) -> tier - 2 | AE82: tier - 1 | AF82: =IF(AE82="?",$AF$6,AE82) -> tier - 1 | AI82: R1011 | AJ82: =IF(AI82="?","Unknown",AI82) -> R1011 | AS82: Id81 | AT82: 45.65 | AU82: 5.11 | AV82: No | AW82: No | AX82: Yes | AY82: Yes | AZ82: 1 | BA82: Gwen M. | BB82: Normal | BC82: Obesity
A83: Id82 | B83: 52.9 | C83: 5.34 | D83: No | E83: No | F83: No | G83: No major surgery | H83: yes | R83: Oct | S83: 2003 | U83: =SUBSTITUTE(R83,"?","Sep") -> Oct | V83: =IF(S83="?",ROUND(AVERAGEIF($S$5:$S$2347,"<>?"),0),S83) -> 2003 | Y83: yes | Z83: =IF(Y83="?",$Z$6,Y83) -> yes | AB83: tier - 2 | AC83: =IF(AB83="?",$AC$6,AB83) -> tier - 2 | AE83: tier - 3 | AF83: =IF(AE83="?",$AF$6,AE83) -> tier - 3 | AI83: R1011 | AJ83: =IF(AI83="?","Unknown",AI83) -> R1011 | AS83: Id82 | AT83: 52.9 | AU83: 5.34 | AV83: No | AW83: No | AX83: No | AY83: Yes | AZ83: 0 | BA83: Patrick | BB83: Normal | BC83: Obesity
A84: Id83 | B84: 45.41 | C84: 4.03 | D84: yes | E84: No | F84: No | G84: 1 | H84: yes | R84: Aug | S84: 2003 | U84: =SUBSTITUTE(R84,"?","Sep") -> Aug | V84: =IF(S84="?",ROUND(AVERAGEIF($S$5:$S$2347,"<>?"),0),S84) -> 2003 | Y84: yes | Z84: =IF(Y84="?",$Z$6,Y84) -> yes | AB84: tier - 2 | AC84: =IF(AB84="?",$AC$6,AB84) -> tier - 2 | AE84: tier - 2 | AF84: =IF(AE84="?",$AF$6,AE84) -> tier - 2 | AI84: R1011 | AJ84: =IF(AI84="?","Unknown",AI84) -> R1011 | AS84: Id83 | AT84: 45.41 | AU84: 4.03 | AV84: No | AW84: No | AX84: Yes | AY84: Yes | AZ84: 1 | BA84: Kate | BB84: Normal | BC84: Obesity
A85: Id84 | B85: 49.41 | C85: 4.23 | D85: yes | E85: No | F85: Yes | G85: 1 | H85: yes | R85: Nov | S85: 2003 | U85: =SUBSTITUTE(R85,"?","Sep") -> Nov | V85: =IF(S85="?",ROUND(AVERAGEIF($S$5:$S$2347,"<>?"),0),S85) -> 2003 | Y85: yes | Z85: =IF(Y85="?",$Z$6,Y85) -> yes | AB85: tier - 2 | AC85: =IF(AB85="?",$AC$6,AB85) -> tier - 2 | AE85: tier - 2 | AF85: =IF(AE85="?",$AF$6,AE85) -> tier - 2 | AI85: R1011 | AJ85: =IF(AI85="?","Unknown",AI85) -> R1011 | AS85: Id84 | AT85: 49.41 | AU85: 4.23 | AV85: No | AW85: Yes | AX85: Yes | AY85: Yes | AZ85: 1 | BA85: Kevin | BB85: Normal | BC85: Obesity
A86: Id85 | B86: 31.825 | C86: 4.06 | D86: No | E86: No | F86: No | G86: 2 | H86: yes | R86: Dec | S86: 2002 | U86: =SUBSTITUTE(R86,"?","Sep") -> Dec | V86: =IF(S86="?",ROUND(AVERAGEIF($S$5:$S$2347,"<>?"),0),S86) -> 2002 | Y86: yes | Z86: =IF(Y86="?",$Z$6,Y86) -> yes | AB86: tier - 2 | AC86: =IF(AB86="?",$AC$6,AB86) -> tier - 2 | AE86: tier - 3 | AF86: =IF(AE86="?",$AF$6,AE86) -> tier - 3 | AI86: R1013 | AJ86: =IF(AI86="?","Unknown",AI86) -> R1013 | AS86: Id85 | AT86: 31.825 | AU86: 4.06 | AV86: No | AW86: No | AX86: No | AY86: Yes | AZ86: 2 | BA86: Stephen II | BB86: Normal | BC86: Obesity
A87: Id86 | B87: 51.28 | C87: 4.68 | D87: No | E87: No | F87: No | G87: 2 | H87: yes | R87: Oct | S87: 1997 | U87: =SUBSTITUTE(R87,"?","Sep") -> Oct | V87: =IF(S87="?",ROUND(AVERAGEIF($S$5:$S$2347,"<>?"),0),S87) -> 1997 | Y87: yes | Z87: =IF(Y87="?",$Z$6,Y87) -> yes | AB87: tier - 2 | AC87: =IF(AB87="?",$AC$6,AB87) -> tier - 2 | AE87: tier - 3 | AF87: =IF(AE87="?",$AF$6,AE87) -> tier - 3 | AI87: R1012 | AJ87: =IF(AI87="?","Unknown",AI87) -> R1012 | AS87: Id86 | AT87: 51.28 | AU87: 4.68 | AV87: No | AW87: No | AX87: No | AY87: Yes | AZ87: 2 | BA87: Philip | BB87: Normal | BC87: Obesity
A88: Id87 | B88: 34.96 | C88: 4.34 | D88: No | E88: No | F88: Yes | G88: 1 | H88: yes | R88: Sep | S88: 2004 | U88: =SUBSTITUTE(R88,"?","Sep") -> Sep | V88: =IF(S88="?",ROUND(AVERAGEIF($S$5:$S$2347,"<>?"),0),S88) -> 2004 | Y88: yes | Z88: =IF(Y88="?",$Z$6,Y88) -> yes | AB88: tier - 2 | AC88: =IF(AB88="?",$AC$6,AB88) -> tier - 2 | AE88: tier - 3 | AF88: =IF(AE88="?",$AF$6,AE88) -> tier - 3 | AI88: R1013 | AJ88: =IF(AI88="?","Unknown",AI88) -> R1013 | AS88: Id87 | AT88: 34.96 | AU88: 4.34 | AV88: No | AW88: Yes | AX88: No | AY88: Yes | AZ88: 1 | BA88: Brett A | BB88: Normal | BC88: Obesity
A89: Id88 | B89: 33.11 | C89: 10.51 | D89: No | E89: No | F89: No | G89: No major surgery | H89: yes | R89: Jul | S89: 2004 | U89: =SUBSTITUTE(R89,"?","Sep") -> Jul | V89: =IF(S89="?",ROUND(AVERAGEIF($S$5:$S$2347,"<>?"),0),S89) -> 2004 | Y89: yes | Z89: =IF(Y89="?",$Z$6,Y89) -> yes | AB89: tier - 2 | AC89: =IF(AB89="?",$AC$6,AB89) -> tier - 2 | AE89: tier - 3 | AF89: =IF(AE89="?",$AF$6,AE89) -> tier - 3 | AI89: R1013 | AJ89: =IF(AI89="?","Unknown",AI89) -> R1013 | AS89: Id88 | AT89: 33.11 | AU89: 10.51 | AV89: No | AW89: No | AX89: No | AY89: Yes | AZ89: 0 | BA89: Rebecca | BB89: Diabetes | BC89: Obesity
A90: Id89 | B90: 54.74 | C90: 5.84 | D90: yes | E90: No | F90: Yes | G90: 1 | H90: yes | R90: Jun | S90: 2000 | U90: =SUBSTITUTE(R90,"?","Sep") -> Jun | V90: =IF(S90="?",ROUND(AVERAGEIF($S$5:$S$2347,"<>?"),0),S90) -> 2000 | Y90: yes | Z90: =IF(Y90="?",$Z$6,Y90) -> yes | AB90: tier - 2 | AC90: =IF(AB90="?",$AC$6,AB90) -> tier - 2 | AE90: tier - 1 | AF90: =IF(AE90="?",$AF$6,AE90) -> tier - 1 | AI90: R1013 | AJ90: =IF(AI90="?","Unknown",AI90) -> R1013 | AS90: Id89 | AT90: 54.74 | AU90: 5.84 | AV90: No | AW90: Yes | AX90: Yes | AY90: Yes | AZ90: 1 | BA90: Kelley | BB90: Prediabetes | BC90: Obesity
A91: Id90 | B91: 32.56 | C91: 5.41 | D91: No | E91: No | F91: Yes | G91: 1 | H91: yes | R91: Jun | S91: 1998 | U91: =SUBSTITUTE(R91,"?","Sep") -> Jun | V91: =IF(S91="?",ROUND(AVERAGEIF($S$5:$S$2347,"<>?"),0),S91) -> 1998 | Y91: yes | Z91: =IF(Y91="?",$Z$6,Y91) -> yes | AB91: tier - 2 | AC91: =IF(AB91="?",$AC$6,AB91) -> tier - 2 | AE91: tier - 2 | AF91: =IF(AE91="?",$AF$6,AE91) -> tier - 2 | AI91: R1013 | AJ91: =IF(AI91="?","Unknown",AI91) -> R1013 | AS91: Id90 | AT91: 32.56 | AU91: 5.41 | AV91: No | AW91: Yes | AX91: No | AY91: Yes | AZ91: 1 | BA91: Abigail K | BB91: Normal | BC91: Obesity
A92: Id91 | B92: 39.05 | C92: 6.06 | D92: No | E92: No | F92: No | G92: 1 | H92: yes | R92: Nov | S92: 2001 | U92: =SUBSTITUTE(R92,"?","Sep") -> Nov | V92: =IF(S92="?",ROUND(AVERAGEIF($S$5:$S$2347,"<>?"),0),S92) -> 2001 | Y92: yes | Z92: =IF(Y92="?",$Z$6,Y92) -> yes | AB92: tier - 2 | AC92: =IF(AB92="?",$AC$6,AB92) -> tier - 2 | AE92: tier - 1 | AF92: =IF(AE92="?",$AF$6,AE92) -> tier - 1 | AI92: R1012 | AJ92: =IF(AI92="?","Unknown",AI92) -> R1012 | AS92: Id91 | AT92: 39.05 | AU92: 6.06 | AV92: No | AW92: No | AX92: No | AY92: Yes | AZ92: 1 | BA92: Hope | BB92: Prediabetes | BC92: Obesity
A93: Id92 | B93: 42.75 | C93: 4.22 | D93: No | E93: No | F93: No | G93: No major surgery | H93: yes | R93: Dec | S93: 2002 | U93: =SUBSTITUTE(R93,"?","Sep") -> Dec | V93: =IF(S93="?",ROUND(AVERAGEIF($S$5:$S$2347,"<>?"),0),S93) -> 2002 | Y93: yes | Z93: =IF(Y93="?",$Z$6,Y93) -> yes | AB93: tier - 2 | AC93: =IF(AB93="?",$AC$6,AB93) -> tier - 2 | AE93: tier - 3 | AF93: =IF(AE93="?",$AF$6,AE93) -> tier - 3 | AI93: R1012 | AJ93: =IF(AI93="?","Unknown",AI93) -> R1012 | AS93: Id92 | AT93: 42.75 | AU93: 4.22 | AV93: No | AW93: No | AX93: No | AY93: Yes | AZ93: 0 | BA93: Elyse M. | BB93: Normal | BC93: Obesity
A94: Id93 | B94: 50.58 | C94: 5.12 | D94: No | E94: No | F94: No | G94: 2 | H94: yes | R94: Dec | S94: 1999 | U94: =SUBSTITUTE(R94,"?","Sep") -> Dec | V94: =IF(S94="?",ROUND(AVERAGEIF($S$5:$S$2347,"<>?"),0),S94) -> 1999 | Y94: yes | Z94: =IF(Y94="?",$Z$6,Y94) -> yes | AB94: tier - 2 | AC94: =IF(AB94="?",$AC$6,AB94) -> tier - 2 | AE94: tier - 2 | AF94: =IF(AE94="?",$AF$6,AE94) -> tier - 2 | AI94: R1013 | AJ94: =IF(AI94="?","Unknown",AI94) -> R1013 | AS94: Id93 | AT94: 50.58 | AU94: 5.12 | AV94: No | AW94: No | AX94: No | AY94: Yes | AZ94: 2 | BA94: Nicholas | BB94: Normal | BC94: Obesity
A95: Id94 | B95: 30.495 | C95: 4.57 | D95: yes | E95: No | F95: No | G95: No major surgery | H95: yes | R95: Oct | S95: 2002 | U95: =SUBSTITUTE(R95,"?","Sep") -> Oct | V95: =IF(S95="?",ROUND(AVERAGEIF($S$5:$S$2347,"<>?"),0),S95) -> 2002 | Y95: yes | Z95: =IF(Y95="?",$Z$6,Y95) -> yes | AB95: tier - 2 | AC95: =IF(AB95="?",$AC$6,AB95) -> tier - 2 | AE95: tier - 2 | AF95: =IF(AE95="?",$AF$6,AE95) -> tier - 2 | AI95: R1013 | AJ95: =IF(AI95="?","Unknown",AI95) -> R1013 | AS95: Id94 | AT95: 30.495 | AU95: 4.57 | AV95: No | AW95: No | AX95: Yes | AY95: Yes | AZ95: 0 | BA95: David | BB95: Normal | BC95: Obesity
A96: Id95 | B96: 48.31 | C96: 9.58 | D96: yes | E96: No | F96: No | G96: 2 | H96: yes | R96: Oct | S96: 1999 | U96: =SUBSTITUTE(R96,"?","Sep") -> Oct | V96: =IF(S96="?",ROUND(AVERAGEIF($S$5:$S$2347,"<>?"),0),S96) -> 1999 | Y96: yes | Z96: =IF(Y96="?",$Z$6,Y96) -> yes | AB96: tier - 2 | AC96: =IF(AB96="?",$AC$6,AB96) -> tier - 2 | AE96: tier - 3 | AF96: =IF(AE96="?",$AF$6,AE96) -> tier - 3 | AI96: R1013 | AJ96: =IF(AI96="?","Unknown",AI96) -> R1013 | AS96: Id95 | AT96: 48.31 | AU96: 9.58 | AV96: No | AW96: No | AX96: Yes | AY96: Yes | AZ96: 2 | BA96: Natalie | BB96: Diabetes | BC96: Obesity
A97: Id96 | B97: 48.99 | C97: 9.78 | D97: yes | E97: No | F97: No | G97: 1 | H97: yes | R97: Jul | S97: 1998 | U97: =SUBSTITUTE(R97,"?","Sep") -> Jul | V97: =IF(S97="?",ROUND(AVERAGEIF($S$5:$S$2347,"<>?"),0),S97) -> 1998 | Y97: yes | Z97: =IF(Y97="?",$Z$6,Y97) -> yes | AB97: tier - 2 | AC97: =IF(AB97="?",$AC$6,AB97) -> tier - 2 | AE97: tier - 2 | AF97: =IF(AE97="?",$AF$6,AE97) -> tier - 2 | AI97: R1013 | AJ97: =IF(AI97="?","Unknown",AI97) -> R1013 | AS97: Id96 | AT97: 48.99 | AU97: 9.78 | AV97: No | AW97: No | AX97: Yes | AY97: Yes | AZ97: 1 | BA97: Thomas | BB97: Diabetes | BC97: Obesity
A98: Id97 | B98: 38.39 | C98: 4.11 | D98: yes | E98: No | F98: No | G98: No major surgery | H98: yes | R98: Jul | S98: 1995 | U98: =SUBSTITUTE(R98,"?","Sep") -> Jul | V98: =IF(S98="?",ROUND(AVERAGEIF($S$5:$S$2347,"<>?"),0),S98) -> 1995 | Y98: yes | Z98: =IF(Y98="?",$Z$6,Y98) -> yes | AB98: tier - 2 | AC98: =IF(AB98="?",$AC$6,AB98) -> tier - 2 | AE98: tier - 2 | AF98: =IF(AE98="?",$AF$6,AE98) -> tier - 2 | AI98: R1012 | AJ98: =IF(AI98="?","Unknown",AI98) -> R1012 | AS98: Id97 | AT98: 38.39 | AU98: 4.11 | AV98: No | AW98: No | AX98: Yes | AY98: Yes | AZ98: 0 | BA98: Pamela J. | BB98: Normal | BC98: Obesity
A99: Id98 | B99: 44.34 | C99: 4.02 | D99: yes | E99: No | F99: No | G99: 2 | H99: yes | R99: Nov | S99: 1997 | U99: =SUBSTITUTE(R99,"?","Sep") -> Nov | V99: =IF(S99="?",ROUND(AVERAGEIF($S$5:$S$2347,"<>?"),0),S99) -> 1997 | Y99: yes | Z99: =IF(Y99="?",$Z$6,Y99) -> yes | AB99: tier - 2 | AC99: =IF(AB99="?",$AC$6,AB99) -> tier - 2 | AE99: tier - 2 | AF99: =IF(AE99="?",$AF$6,AE99) -> tier - 2 | AI99: R1012 | AJ99: =IF(AI99="?","Unknown",AI99) -> R1012 | AS99: Id98 | AT99: 44.34 | AU99: 4.02 | AV99: No | AW99: No | AX99: Yes | AY99: Yes | AZ99: 2 | BA99: Jessica | BB99: Normal | BC99: Obesity
A100: Id99 | B100: 41.51 | C100: 6.92 | D100: No | E100: No | F100: No | G100: No major surgery | H100: yes | R100: Dec | S100: 1998 | U100: =SUBSTITUTE(R100,"?","Sep") -> Dec | V100: =IF(S100="?",ROUND(AVERAGEIF($S$5:$S$2347,"<>?"),0),S100) -> 1998 | Y100: yes | Z100: =IF(Y100="?",$Z$6,Y100) -> yes | AB100: tier - 2 | AC100: =IF(AB100="?",$AC$6,AB100) -> tier - 2 | AE100: tier - 3 | AF100: =IF(AE100="?",$AF$6,AE100) -> tier - 3 | AI100: R1013 | AJ100: =IF(AI100="?","Unknown",AI100) -> R1013 | AS100: Id99 | AT100: 41.51 | AU100: 6.92 | AV100: No | AW100: No | AX100: No | AY100: Yes | AZ100: 0 | BA100: Ron N | BB100: Diabetes | BC100: Obesity
...

Sheet Hospitalisation Details
A1: Customer ID | B1: year | C1: month | D1: date | E1: children | F1: charges | G1: Hospital tier | H1: City tier | I1: State ID
A2: Id2335 | B2: 1992 | C2: Jul | D2: 9 | E2: 0 | F2: 563.84 | G2: tier - 2 | H2: tier - 3 | I2: R1013 | L2: Customer ID | M2: Date of Birth | N2: Age | O2: Proper Hospital tier | P2: Proper City tier | Q2: Proper Sate ID | R2: Charges $ | S2: Proper Month | T2: Proper Year | U2: date
A3: Id2334 | B3: 1992 | C3: Nov | D3: 30 | E3: 0 | F3: 570.62 | G3: tier - 2 | H3: tier - 1 | I3: R1013 | L3: Id2335 | M3: 09-07-1992 | N3: 30 | O3: tier - 2 | P3: tier - 3 | Q3: R1013 | R3: 564 | S3: Jul | T3: 1992 | U3: 9
A4: Id2333 | B4: 1993 | C4: Jun | D4: 30 | E4: 0 | F4: 600 | G4: tier - 2 | H4: tier - 1 | I4: R1013 | L4: Id2334 | M4: 30-11-1992 | N4: 30 | O4: tier - 2 | P4: tier - 1 | Q4: R1013 | R4: 571 | S4: Nov | T4: 1992 | U4: 30
A5: Id2332 | B5: 1992 | C5: Sep | D5: 13 | E5: 0 | F5: 604.54 | G5: tier - 3 | H5: tier - 3 | I5: R1013 | L5: Id2333 | M5: 30-06-1993 | N5: 29 | O5: tier - 2 | P5: tier - 1 | Q5: R1013 | R5: 600 | S5: Jun | T5: 1993 | U5: 30
A6: Id2331 | B6: 1998 | C6: Jul | D6: 27 | E6: 0 | F6: 637.26 | G6: tier - 3 | H6: tier - 3 | I6: R1013 | L6: Id2332 | M6: 13-09-1992 | N6: 30 | O6: tier - 3 | P6: tier - 3 | Q6: R1013 | R6: 605 | S6: Sep | T6: 1992 | U6: 13
A7: Id2330 | B7: 2001 | C7: Nov | D7: 20 | E7: 0 | F7: 646.14 | G7: tier - 3 | H7: tier - 3 | I7: R1012 | L7: Id2331 | M7: 27-07-1998 | N7: 24 | O7: tier - 3 | P7: tier - 3 | Q7: R1013 | R7: 637 | S7: Jul | T7: 1998 | U7: 27
A8: Id2329 | B8: 1993 | C8: Jun | D8: 1 | E8: 0 | F8: 650 | G8: tier - 3 | H8: tier - 3 | I8: R1013 | L8: Id2330 | M8: 20-11-2001 | N8: 21 | O8: tier - 3 | P8: tier - 3 | Q8: R1012 | R8: 646 | S8: Nov | T8: 2001 | U8: 20
A9: Id2328 | B9: 1995 | C9: Jul | D9: 4 | E9: 0 | F9: 650 | G9: tier - 3 | H9: tier - 3 | I9: R1013 | L9: Id2329 | M9: 01-06-1993 | N9: 30 | O9: tier - 3 | P9: tier - 3 | Q9: R1013 | R9: 650 | S9: Jun | T9: 1993 | U9: 1
A10: Id2327 | B10: 2002 | C10: Nov | D10: 29 | E10: 0 | F10: 668 | G10: tier - 3 | H10: tier - 2 | I10: R1012 | L10: Id2328 | M10: 04-07-1995 | N10: 27 | O10: tier - 3 | P10: tier - 3 | Q10: R1013 | R10: 650 | S10: Jul | T10: 1995 | U10: 4
A11: Id2326 | B11: 1997 | C11: Nov | D11: 9 | E11: 0 | F11: 670 | G11: tier - 3 | H11: tier - 3 | I11: R1013 | L11: Id2327 | M11: 29-11-2002 | N11: 20 | O11: tier - 3 | P11: tier - 2 | Q11: R1012 | R11: 668 | S11: Nov | T11: 2002 | U11: 29
A12: Id2325 | B12: 2001 | C12: Sep | D12: 12 | E12: 0 | F12: 687.54 | G12: tier - 3 | H12: tier - 2 | I12: R1013 | L12: Id2326 | M12: 09-11-1997 | N12: 25 | O12: tier - 3 | P12: tier - 3 | Q12: R1013 | R12: 670 | S12: Nov | T12: 1997 | U12: 9
A13: Id2324 | B13: 1999 | C13: Dec | D13: 26 | E13: 0 | F13: 700 | G13: ? | H13: tier - 3 | I13: R1013 | L13: Id2325 | M13: 12-09-2001 | N13: 21 | O13: tier - 3 | P13: tier - 2 | Q13: R1013 | R13: 688 | S13: Sep | T13: 2001 | U13: 12
A14: Id2323 | B14: 1999 | C14: Dec | D14: 14 | E14: 0 | F14: 722.99 | G14: tier - 3 | H14: tier - 1 | I14: R1013 | L14: Id2324 | M14: 26-12-1999 | N14: 23 | O14: tier - 2 | P14: tier - 3 | Q14: R1013 | R14: 700 | S14: Dec | T14: 1999 | U14: 26
... A1050: Id1290 | B1050: 1977 | C1050: Jul | D1050: 26 | E1050: 2 | F1050: 8527.53 | G1050: tier - 2 | H1050: tier - 2 | I1050: R1013 | L1050: Id1291 | M1050: 13-08-1979 | N1050: 43 | O1050: tier - 2 | P1050: tier - 2 | Q1050: R1011 | R1050: 8522 | S1050: Aug | T1050: 1979 | U1050: 13
A1051: Id1289 | B1051: ? | C1051: Jul | D1051: 24 | E1051: 0 | F1051: 8534.67 | G1051: tier - 2 | H1051: tier - 3 | I1051: R1024 | L1051: Id1290 | M1051: 26-07-1977 | N1051: 45 | O1051: tier - 2 | P1051: tier - 2 | Q1051: R1013 | R1051: 8528 | S1051: Jul | T1051: 1977 | U1051: 26
A1052: Id1288 | B1052: 1981 | C1052: Dec | D1052: 27 | E1052: 3 | F1052: 8538.29 | G1052: tier - 2 | H1052: tier - 3 | I1052: R1024 | L1052: Id1289 | M1052: 24-07-1983 | N1052: 39 | O1052: tier - 2 | P1052: tier - 3 | Q1052: R1024 | R1052: 8535 | S1052: Jul | T1052: 1983 | U1052: 24
A1053: Id1287 | B1053: 1975 | C1053: Nov | D1053: 6 | E1053: 1 | F1053: 8539.67 | G1053: tier - 2 | H1053: tier - 3 | I1053: R1011 | L1053: Id1288 | M1053: 27-12-1981 | N1053: 41 | O1053: tier - 2 | P1053: tier - 3 | Q1053: R1024 | R1053: 8538 | S1053: Dec | T1053: 1981 | U1053: 27
A1054: Id1286 | B1054: ? | C1054: Dec | D1054: 12 | E1054: 1 | F1054: 8547.69 | G1054: tier - 2 | H1054: tier - 1 | I1054: R1013 | L1054: Id1287 | M1054: 06-11-1975 | N1054: 47 | O1054: tier - 2 | P1054: tier - 3 | Q1054: R1011 | R1054: 8540 | S1054: Nov | T1054: 1975 | U1054: 6
A1055: Id1285 | B1055: 1975 | C1055: Aug | D1055: 6 | E1055: 1 | F1055: 8551.35 | G1055: tier - 2 | H1055: tier - 2 | I1055: R1011 | L1055: Id1286 | M1055: 12-12-1983 | N1055: 39 | O1055: tier - 2 | P1055: tier - 1 | Q1055: R1013 | R1055: 8548 | S1055: Dec | T1055: 1983 | U1055: 12
A1056: Id1284 | B1056: 1975 | C1056: Aug | D1056: 21 | E1056: 1 | F1056: 8556.91 | G1056: tier - 2 | H1056: tier - 1 | I1056: R1011 | L1056: Id1285 | M1056: 06-08-1975 | N1056: 47 | O1056: tier - 2 | P1056: tier - 2 | Q1056: R1011 | R1056: 8551 | S1056: Aug | T1056: 1975 | U1056: 6
A1057: Id1283 | B1057: 1988 | C1057: Sep | D1057: 21 | E1057: 3 | F1057: 8567.25 | G1057: tier - 2 | H1057: tier - 1 | I1057: R1012 | L1057: Id1284 | M1057: 21-08-1975 | N1057: 47 | O1057: tier - 2 | P1057: tier - 1 | Q1057: R1011 | R1057: 8557 | S1057: Aug | T1057: 1975 | U1057: 21
A1058: Id1282 | B1058: 1975 | C1058: Sep | D1058: 26 | E1058: 1 | F1058: 8569.86 | G1058: tier - 2 | H1058: tier - 3 | I1058: R1013 | L1058: Id1283 | M1058: 21-09-1988 | N1058: 34 | O1058: tier - 2 | P1058: tier - 1 | Q1058: R1012 | R1058: 8567 | S1058: Sep | T1058: 1988 | U1058: 21
A1059: Id1281 | B1059: 1982 | C1059: Dec | D1059: 6 | E1059: 3 | F1059: 8572.04 | G1059: tier - 2 | H1059: tier - 2 | I1059: R1021 | L1059: Id1282 | M1059: 26-09-1975 | N1059: 47 | O1059: tier - 2 | P1059: tier - 3 | Q1059: R1013 | R1059: 8570 | S1059: Sep | T1059: 1975 | U1059: 26
A1060: Id1280 | B1060: 1987 | C1060: Nov | D1060: 11 | E1060: 3 | F1060: 8573.3 | G1060: tier - 2 | H1060: tier - 2 | I1060: R1021 | L1060: Id1281 | M1060: 06-12-1982 | N1060: 40 | O1060: tier - 2 | P1060: tier - 2 | Q1060: R1021 | R1060: 8572 | S1060: Dec | T1060: 1982 | U1060: 6
A1061: Id1279 | B1061: 1983 | C1061: Dec | D1061: 30 | E1061: 5 | F1061: 8582.3 | G1061: tier - 2 | H1061: tier - 1 | I1061: R1013 | L1061: Id1280 | M1061: 11-11-1987 | N1061: 35 | O1061: tier - 2 | P1061: tier - 2 | Q1061: R1021 | R1061: 8573 | S1061: Nov | T1061: 1987 | U1061: 11
A1062: Id1278 | B1062: 1983 | C1062: Jul | D1062: 25 | E1062: 5 | F1062: 8596.83 | G1062: tier - 2 | H1062: tier - 3 | I1062: R1013 | L1062: Id1279 | M1062: 30-12-1983 | N1062: 39 | O1062: tier - 2 | P1062: tier - 1 | Q1062: R1013 | R1062: 8582 | S1062: Dec | T1062: 1983 | U1062: 30
A1063: Id1277 | B1063: 1973 | C1063: Jul | D1063: 11 | E1063: 0 | F1063: 8601.33 | G1063: tier - 2 | H1063: tier - 1 | I1063: R1013 | L1063: Id1278 | M1063: 25-07-1983 | N1063: 39 | O1063: tier - 2 | P1063: tier - 3 | Q1063: R1013 | R1063: 8597 | S1063: Jul | T1063: 1983 | U1063: 25
A1064: Id1276 | B1064: 1977 | C1064: Sep | D1064: 24 | E1064: 2 | F1064: 8603.82 | G1064: tier - 2 | H1064: tier - 1 | I1064: R1019 | L1064: Id1277 | M1064: 11-07-1973 | N1064: 49 | O1064: tier - 2 | P1064: tier - 1 | Q1064: R1013 | R1064: 8601 | S1064: Jul | T1064: 1973 | U1064: 11
A1065: Id1275 | B1065: 1977 | C1065: Nov | D1065: 12 | E1065: 2 | F1065: 8604.48 | G1065: tier - 3 | H1065: tier - 2 | I1065: R1016 | L1065: Id1276 | M1065: 24-09-1977 | N1065: 45 | O1065: tier - 2 | P1065: tier - 1 | Q1065: R1019 | R1065: 8604 | S1065: Sep | T1065: 1977 | U1065: 24
A1066: Id1274 | B1066: 1977 | C1066: Oct | D1066: 15 | E1066: 3 | F1066: 8605.36 | G1066: tier - 2 | H1066: tier - 2 | I1066: R1013 | L1066: Id1275 | M1066: 12-11-1977 | N1066: 45 | O1066: tier - 3 | P1066: tier - 2 | Q1066: R1016 | R1066: 8604 | S1066: Nov | T1066: 1977 | U1066: 12
... A2341: Id1 | B2341: 1968 | C2341: Oct | D2341: 12 | E2341: 0 | F2341: 63770.43 | G2341: tier - 1 | H2341: tier - 3 | I2341: R1013 | L2341: Id2 | M2341: 08-06-1977 | N2341: 46 | O2341: tier - 2 | P2341: tier - 3 | Q2341: R1013 | R2341: 62593 | S2341: Jun | T2341: 1977 | U2341: 8
L2342: Id1 | M2342: 12-10-1968 | N2342: 54 | O2342: tier - 1 | P2342: tier - 3 | Q2342: R1013 | R2342: 63770 | S2342: Oct | T2342: 1968 | U2342: 12

Sheet Healthcare
A1: Customer ID | B1: First Name | C1: BMI | D1: HBA1C | E1: Heart Issues | F1: Any Transplants | G1: Cancer History | H1: Number of Major Surgeries | I1: Smoker | J1: Weight Status | K1: Diabetes Status | L1: Date of Birth | M1: Charges | N1: Hospital Tier | O1: City Tier | P1: State ID | Q1: Age | R1: Date | S1: Month | T1: Year
A2: Id1 | B2: =VLOOKUP(A2,'Medical Examinations'!$AS$1:$BC$2336,9,) -> Kelly | C2: =VLOOKUP(A2,'Medical Examinations'!$AS$1:$BC$2336,2,) -> 47.41 | D2: =VLOOKUP(A2,'Medical Examinations'!$AS$1:$BC$2336,3,) -> 7.47 | E2: =VLOOKUP(A2,'Medical Examinations'!$AS$1:$BC$2336,6,) -> No | F2: =VLOOKUP(A2,'Medical Examinations'!$AS$1:$BC$2336,4,) -> No | G2: =VLOOKUP(A2,'Medical Examinations'!$AS$1:$BC$2336,5,) -> No | H2: =VLOOKUP(A2,'Medical Examinations'!$AS$1:$BC$2336,8,) -> 0 | I2: =VLOOKUP(A2,'Medical Examinations'!$AS$1:$BC$2336,7,) -> Yes | J2: =VLOOKUP(A2,'Medical Examinations'!$AS$1:$BC$2336,11,) -> Obesity | K2: =VLOOKUP(A2,'Medical Examinations'!$AS$1:$BC$2336,10,) -> Diabetes | L2: =VLOOKUP(A2,'Hospitalisation Details'!$L$2:$R$2342,2,) -> 12-10-1968 | M2: =VLOOKUP(A2,'Hospitalisation Details'!$L$2:$R$2345,7,) -> 63770 | N2: =VLOOKUP(A2,'Hospitalisation Details'!$L$2:$R$2342,4,) -> tier - 1 | O2: =VLOOKUP(A2,'Hospitalisation Details'!$L$2:$R$2342,5,) -> tier - 3 | P2: =VLOOKUP(A2,'Hospitalisation Details'!$L$2:$R$2342,6,) -> R1013 | Q2: =VLOOKUP(A2,'Hospitalisation Details'!$L$2:$R$2342,3,) -> 54 | R2: =VLOOKUP(A2,'Hospitalisation Details'!$L$2:$U$2342,10,) -> 12 | S2: =VLOOKUP(A2,'Hospitalisation Details'!$L$2:$U$2342,8,) -> Oct | T2: =VLOOKUP(A2,'Hospitalisation Details'!$L$2:$U$2342,9,) -> 1968
A3: Id2 | B3: =VLOOKUP(A3,'Medical Examinations'!$AS$1:$BC$2336,9,) -> Matthew D | C3: =VLOOKUP(A3,'Medical Examinations'!$AS$1:$BC$2336,2,) -> 30.36 | D3: =VLOOKUP(A3,'Medical Examinations'!$AS$1:$BC$2336,3,) -> 5.77 | E3: =VLOOKUP(A3,'Medical Examinations'!$AS$1:$BC$2336,6,) -> No | F3: =VLOOKUP(A3,'Medical Examinations'!$AS$1:$BC$2336,4,) -> No | G3: =VLOOKUP(A3,'Medical Examinations'!$AS$1:$BC$2336,5,) -> No | H3: =VLOOKUP(A3,'Medical Examinations'!$AS$1:$BC$2336,8,) -> 0 | I3: =VLOOKUP(A3,'Medical Examinations'!$AS$1:$BC$2336,7,) -> Yes | J3: =VLOOKUP(A3,'Medical Examinations'!$AS$1:$BC$2336,11,) -> Obesity | K3: =VLOOKUP(A3,'Medical Examinations'!$AS$1:$BC$2336,10,) -> Prediabetes | L3: =VLOOKUP(A3,'Hospitalisation Details'!$L$2:$R$2342,2,) -> 08-06-1977 | M3: =VLOOKUP(A3,'Hospitalisation Details'!$L$2:$R$2345,7,) -> 62593 | N3: =VLOOKUP(A3,'Hospitalisation Details'!$L$2:$R$2342,4,) -> tier - 2 | O3: =VLOOKUP(A3,'Hospitalisation Details'!$L$2:$R$2342,5,) -> tier - 3 | P3: =VLOOKUP(A3,'Hospitalisation Details'!$L$2:$R$2342,6,) -> R1013 | Q3: =VLOOKUP(A3,'Hospitalisation Details'!$L$2:$R$2342,3,) -> 46 | R3: =VLOOKUP(A3,'Hospitalisation Details'!$L$2:$U$2342,10,) -> 8 | S3: =VLOOKUP(A3,'Hospitalisation Details'!$L$2:$U$2342,8,) -> Jun | T3: =VLOOKUP(A3,'Hospitalisation Details'!$L$2:$U$2342,9,) -> 1977
A4: Id3 | B4: =VLOOKUP(A4,'Medical Examinations'!$AS$1:$BC$2336,9,) -> Phil | C4: =VLOOKUP(A4,'Medical Examinations'!$AS$1:$BC$2336,2,) -> 34.485 | D4: =VLOOKUP(A4,'Medical Examinations'!$AS$1:$BC$2336,3,) -> 11.87 | E4: =VLOOKUP(A4,'Medical Examinations'!$AS$1:$BC$2336,6,) -> Yes | F4: =VLOOKUP(A4,'Medical Examinations'!$AS$1:$BC$2336,4,) -> No | G4: =VLOOKUP(A4,'Medical Examinations'!$AS$1:$BC$2336,5,) -> No | H4: =VLOOKUP(A4,'Medical Examinations'!$AS$1:$BC$2336,8,) -> 2 | I4: =VLOOKUP(A4,'Medical Examinations'!$AS$1:$BC$2336,7,) -> Yes | J4: =VLOOKUP(A4,'Medical Examinations'!$AS$1:$BC$2336,11,) -> Obesity | K4: =VLOOKUP(A4,'Medical Examinations'!$AS$1:$BC$2336,10,) -> Diabetes | L4: =VLOOKUP(A4,'Hospitalisation Details'!$L$2:$R$2342,2,) -> 11-09-1970 | M4: =VLOOKUP(A4,'Hospitalisation Details'!$L$2:$R$2345,7,) -> 60021 | N4: =VLOOKUP(A4,'Hospitalisation Details'!$L$2:$R$2342,4,) -> tier - 1 | O4: =VLOOKUP(A4,'Hospitalisation Details'!$L$2:$R$2342,5,) -> tier - 1 | P4: =VLOOKUP(A4,'Hospitalisation Details'!$L$2:$R$2342,6,) -> R1012 | Q4: =VLOOKUP(A4,'Hospitalisation Details'!$L$2:$R$2342,3,) -> 52 | R4: =VLOOKUP(A4,'Hospitalisation Details'!$L$2:$U$2342,10,) -> 11 | S4: =VLOOKUP(A4,'Hospitalisation Details'!$L$2:$U$2342,8,) -> Sep | T4: =VLOOKUP(A4,'Hospitalisation Details'!$L$2:$U$2342,9,) -> 1970
A5: Id4 | B5: =VLOOKUP(A5,'Medical Examinations'!$AS$1:$BC$2336,9,) -> Kelsey | C5: =VLOOKUP(A5,'Medical Examinations'!$AS$1:$BC$2336,2,) -> 38.095 | D5: =VLOOKUP(A5,'Medical Examinations'!$AS$1:$BC$2336,3,) -> 6.05 | E5: =VLOOKUP(A5,'Medical Examinations'!$AS$1:$BC$2336,6,) -> No | F5: =VLOOKUP(A5,'Medical Examinations'!$AS$1:$BC$2336,4,) -> No | G5: =VLOOKUP(A5,'Medical Examinations'!$AS$1:$BC$2336,5,) -> No | H5: =VLOOKUP(A5,'Medical Examinations'!$AS$1:$BC$2336,8,) -> 0 | I5: =VLOOKUP(A5,'Medical Examinations'!$AS$1:$BC$2336,7,) -> Yes | J5: =VLOOKUP(A5,'Medical Examinations'!$AS$1:$BC$2336,11,) -> Obesity | K5: =VLOOKUP(A5,'Medical Examinations'!$AS$1:$BC$2336,10,) -> Prediabetes | L5: =VLOOKUP(A5,'Hospitalisation Details'!$L$2:$R$2342,2,) -> 06-06-1991 | M5: =VLOOKUP(A5,'Hospitalisation Details'!$L$2:$R$2345,7,) -> 58571 | N5: =VLOOKUP(A5,'Hospitalisation Details'!$L$2:$R$2342,4,) -> tier - 1 | O5: =VLOOKUP(A5,'Hospitalisation Details'!$L$2:$R$2342,5,) -> tier - 3 | P5: =VLOOKUP(A5,'Hospitalisation Details'!$L$2:$R$2342,6,) -> R1024 | Q5: =VLOOKUP(A5,'Hospitalisation Details'!$L$2:$R$2342,3,) -> 32 | R5: =VLOOKUP(A5,'Hospitalisation Details'!$L$2:$U$2342,10,) -> 6 | S5: =VLOOKUP(A5,'Hospitalisation Details'!$L$2:$U$2342,8,) -> Jun | T5: =VLOOKUP(A5,'Hospitalisation Details'!$L$2:$U$2342,9,) -> 1991
A6: Id5 | B6: =VLOOKUP(A6,'Medical Examinations'!$AS$1:$BC$2336,9,) -> Kristyn | C6: =VLOOKUP(A6,'Medical Examinations'!$AS$1:$BC$2336,2,) -> 35.53 | D6: =VLOOKUP(A6,'Medical Examinations'!$AS$1:$BC$2336,3,) -> 5.45 | E6: =VLOOKUP(A6,'Medical Examinations'!$AS$1:$BC$2336,6,) -> No | F6: =VLOOKUP(A6,'Medical Examinations'!$AS$1:$BC$2336,4,) -> No | G6: =VLOOKUP(A6,'Medical Examinations'!$AS$1:$BC$2336,5,) -> No | H6: =VLOOKUP(A6,'Medical Examinations'!$AS$1:$BC$2336,8,) -> 0 | I6: =VLOOKUP(A6,'Medical Examinations'!$AS$1:$BC$2336,7,) -> Yes | J6: =VLOOKUP(A6,'Medical Examinations'!$AS$1:$BC$2336,11,) -> Obesity | K6: =VLOOKUP(A6,'Medical Examinations'!$AS$1:$BC$2336,10,) -> Normal | L6: =VLOOKUP(A6,'Hospitalisation Details'!$L$2:$R$2342,2,) -> 19-06-1989 | M6: =VLOOKUP(A6,'Hospitalisation Details'!$L$2:$R$2345,7,) -> 55135 | N6: =VLOOKUP(A6,'Hospitalisation Details'!$L$2:$R$2342,4,) -> tier - 1 | O6: =VLOOKUP(A6,'Hospitalisation Details'!$L$2:$R$2342,5,) -> tier - 2 | P6: =VLOOKUP(A6,'Hospitalisation Details'!$L$2:$R$2342,6,) -> R1012 | Q6: =VLOOKUP(A6,'Hospitalisation Details'!$L$2:$R$2342,3,) -> 33 | R6: =VLOOKUP(A6,'Hospitalisation Details'!$L$2:$U$2342,10,) -> 19 | S6: =VLOOKUP(A6,'Hospitalisation Details'!$L$2:$U$2342,8,) -> Jun | T6: =VLOOKUP(A6,'Hospitalisation Details'!$L$2:$U$2342,9,) -> 1989
A7: Id6 | B7: =VLOOKUP(A7,'Medical Examinations'!$AS$1:$BC$2336,9,) -> Russell B. | C7: =VLOOKUP(A7,'Medical Examinations'!$AS$1:$BC$2336,2,) -> 32.8 | D7: =VLOOKUP(A7,'Medical Examinations'!$AS$1:$BC$2336,3,) -> 6.59 | E7: =VLOOKUP(A7,'Medical Examinations'!$AS$1:$BC$2336,6,) -> No | F7: =VLOOKUP(A7,'Medical Examinations'!$AS$1:$BC$2336,4,) -> No | G7: =VLOOKUP(A7,'Medical Examinations'!$AS$1:$BC$2336,5,) -> No | H7: =VLOOKUP(A7,'Medical Examinations'!$AS$1:$BC$2336,8,) -> 0 | I7: =VLOOKUP(A7,'Medical Examinations'!$AS$1:$BC$2336,7,) -> Yes | J7: =VLOOKUP(A7,'Medical Examinations'!$AS$1:$BC$2336,11,) -> Obesity | K7: =VLOOKUP(A7,'Medical Examinations'!$AS$1:$BC$2336,10,) -> Diabetes | L7: =VLOOKUP(A7,'Hospitalisation Details'!$L$2:$R$2342,2,) -> 04-08-1962 | M7: =VLOOKUP(A7,'Hospitalisation Details'!$L$2:$R$2345,7,) -> 52591 | N7: =VLOOKUP(A7,'Hospitalisation Details'!$L$2:$R$2342,4,) -> tier - 1 | O7: =VLOOKUP(A7,'Hospitalisation Details'!$L$2:$R$2342,5,) -> tier - 3 | P7: =VLOOKUP(A7,'Hospitalisation Details'!$L$2:$R$2342,6,) -> R1011 | Q7: =VLOOKUP(A7,'Hospitalisation Details'!$L$2:$R$2342,3,) -> 60 | R7: =VLOOKUP(A7,'Hospitalisation Details'!$L$2:$U$2342,10,) -> 4 | S7: =VLOOKUP(A7,'Hospitalisation Details'!$L$2:$U$2342,8,) -> Aug | T7: =VLOOKUP(A7,'Hospitalisation Details'!$L$2:$U$2342,9,) -> 1962
A8: Id7 | B8: =VLOOKUP(A8,'Medical Examinations'!$AS$1:$BC$2336,9,) -> Scott | C8: =VLOOKUP(A8,'Medical Examinations'!$AS$1:$BC$2336,2,) -> 36.4 | D8: =VLOOKUP(A8,'Medical Examinations'!$AS$1:$BC$2336,3,) -> 6.07 | E8: =VLOOKUP(A8,'Medical Examinations'!$AS$1:$BC$2336,6,) -> No | F8: =VLOOKUP(A8,'Medical Examinations'!$AS$1:$BC$2336,4,) -> No | G8: =VLOOKUP(A8,'Medical Examinations'!$AS$1:$BC$2336,5,) -> No | H8: =VLOOKUP(A8,'Medical Examinations'!$AS$1:$BC$2336,8,) -> 0 | I8: =VLOOKUP(A8,'Medical Examinations'!$AS$1:$BC$2336,7,) -> Yes | J8: =VLOOKUP(A8,'Medical Examinations'!$AS$1:$BC$2336,11,) -> Obesity | K8: =VLOOKUP(A8,'Medical Examinations'!$AS$1:$BC$2336,10,) -> Prediabetes | L8: =VLOOKUP(A8,'Hospitalisation Details'!$L$2:$R$2342,2,) -> 27-10-1994 | M8: =VLOOKUP(A8,'Hospitalisation Details'!$L$2:$R$2345,7,) -> 51195 | N8: =VLOOKUP(A8,'Hospitalisation Details'!$L$2:$R$2342,4,) -> tier - 1 | O8: =VLOOKUP(A8,'Hospitalisation Details'!$L$2:$R$2342,5,) -> tier - 3 | P8: =VLOOKUP(A8,'Hospitalisation Details'!$L$2:$R$2342,6,) -> R1011 | Q8: =VLOOKUP(A8,'Hospitalisation Details'!$L$2:$R$2342,3,) -> 28 | R8: =VLOOKUP(A8,'Hospitalisation Details'!$L$2:$U$2342,10,) -> 27 | S8: =VLOOKUP(A8,'Hospitalisation Details'!$L$2:$U$2342,8,) -> Oct | T8: =VLOOKUP(A8,'Hospitalisation Details'!$L$2:$U$2342,9,) -> 1994
A9: Id8 | B9: =VLOOKUP(A9,'Medical Examinations'!$AS$1:$BC$2336,9,) -> Stephen | C9: =VLOOKUP(A9,'Medical Examinations'!$AS$1:$BC$2336,2,) -> 36.96 | D9: =VLOOKUP(A9,'Medical Examinations'!$AS$1:$BC$2336,3,) -> 7.93 | E9: =VLOOKUP(A9,'Medical Examinations'!$AS$1:$BC$2336,6,) -> No | F9: =VLOOKUP(A9,'Medical Examinations'!$AS$1:$BC$2336,4,) -> No | G9: =VLOOKUP(A9,'Medical Examinations'!$AS$1:$BC$2336,5,) -> No | H9: =VLOOKUP(A9,'Medical Examinations'!$AS$1:$BC$2336,8,) -> 3 | I9: =VLOOKUP(A9,'Medical Examinations'!$AS$1:$BC$2336,7,) -> Yes | J9: =VLOOKUP(A9,'Medical Examinations'!$AS$1:$BC$2336,11,) -> Obesity | K9: =VLOOKUP(A9,'Medical Examinations'!$AS$1:$BC$2336,10,) -> Diabetes | L9: =VLOOKUP(A9,'Hospitalisation Details'!$L$2:$R$2342,2,) -> 27-06-1958 | M9: =VLOOKUP(A9,'Hospitalisation Details'!$L$2:$R$2345,7,) -> 49578 | N9: =VLOOKUP(A9,'Hospitalisation Details'!$L$2:$R$2342,4,) -> tier - 2 | O9: =VLOOKUP(A9,'Hospitalisation Details'!$L$2:$R$2342,5,) -> tier - 2 | P9: =VLOOKUP(A9,'Hospitalisation Details'!$L$2:$R$2342,6,) -> R1013 | Q9: =VLOOKUP(A9,'Hospitalisation Details'!$L$2:$R$2342,3,) -> 64 | R9: =VLOOKUP(A9,'Hospitalisation Details'!$L$2:$U$2342,10,) -> 27 | S9: =VLOOKUP(A9,'Hospitalisation Details'!$L$2:$U$2342,8,) -> Jun | T9: =VLOOKUP(A9,'Hospitalisation Details'!$L$2:$U$2342,9,) -> 1958
A10: Id9 | B10: =VLOOKUP(A10,'Medical Examinations'!$AS$1:$BC$2336,9,) -> Patrick R. | C10: =VLOOKUP(A10,'Medical Examinations'!$AS$1:$BC$2336,2,) -> 41.14 | D10: =VLOOKUP(A10,'Medical Examinations'!$AS$1:$BC$2336,3,) -> 9.58 | E10: =VLOOKUP(A10,'Medical Examinations'!$AS$1:$BC$2336,6,) -> Yes | F10: =VLOOKUP(A10,'Medical Examinations'!$AS$1:$BC$2336,4,) -> No | G10: =VLOOKUP(A10,'Medical Examinations'!$AS$1:$BC$2336,5,) -> Yes | H10: =VLOOKUP(A10,'Medical Examinations'!$AS$1:$BC$2336,8,) -> 1 | I10: =VLOOKUP(A10,'Medical Examinations'!$AS$1:$BC$2336,7,) -> Yes | J10: =VLOOKUP(A10,'Medical Examinations'!$AS$1:$BC$2336,11,) -> Obesity | K10: =VLOOKUP(A10,'Medical Examinations'!$AS$1:$BC$2336,10,) -> Diabetes | L10: =VLOOKUP(A10,'Hospitalisation Details'!$L$2:$R$2342,2,) -> 04-09-1963 | M10: =VLOOKUP(A10,'Hospitalisation Details'!$L$2:$R$2345,7,) -> 48970 | N10: =VLOOKUP(A10,'Hospitalisation Details'!$L$2:$R$2342,4,) -> tier - 1 | O10: =VLOOKUP(A10,'Hospitalisation Details'!$L$2:$R$2342,5,) -> tier - 2 | P10: =VLOOKUP(A10,'Hospitalisation Details'!$L$2:$R$2342,6,) -> R1013 | Q10: =VLOOKUP(A10,'Hospitalisation Details'!$L$2:$R$2342,3,) -> 59 | R10: =VLOOKUP(A10,'Hospitalisation Details'!$L$2:$U$2342,10,) -> 4 | S10: =VLOOKUP(A10,'Hospitalisation Details'!$L$2:$U$2342,8,) -> Sep | T10: =VLOOKUP(A10,'Hospitalisation Details'!$L$2:$U$2342,9,) -> 1963
A11: Id10 | B11: =VLOOKUP(A11,'Medical Examinations'!$AS$1:$BC$2336,9,) -> Brooke N. | C11: =VLOOKUP(A11,'Medical Examinations'!$AS$1:$BC$2336,2,) -> 38.06 | D11: =VLOOKUP(A11,'Medical Examinations'!$AS$1:$BC$2336,3,) -> 10.79 | E11: =VLOOKUP(A11,'Medical Examinations'!$AS$1:$BC$2336,6,) -> No | F11: =VLOOKUP(A11,'Medical Examinations'!$AS$1:$BC$2336,4,) -> No | G11: =VLOOKUP(A11,'Medical Examinations'!$AS$1:$BC$2336,5,) -> No | H11: =VLOOKUP(A11,'Medical Examinations'!$AS$1:$BC$2336,8,) -> 0 | I11: =VLOOKUP(A11,'Medical Examinations'!$AS$1:$BC$2336,7,) -> Yes | J11: =VLOOKUP(A11,'Medical Examinations'!$AS$1:$BC$2336,11,) -> Obesity | K11: =VLOOKUP(A11,'Medical Examinations'!$AS$1:$BC$2336,10,) -> Diabetes | L11: =VLOOKUP(A11,'Hospitalisation Details'!$L$2:$R$2342,2,) -> 29-12-1978 | M11: =VLOOKUP(A11,'Hospitalisation Details'!$L$2:$R$2345,7,) -> 48885 | N11: =VLOOKUP(A11,'Hospitalisation Details'!$L$2:$R$2342,4,) -> tier - 1 | O11: =VLOOKUP(A11,'Hospitalisation Details'!$L$2:$R$2342,5,) -> tier - 2 | P11: =VLOOKUP(A11,'Hospitalisation Details'!$L$2:$R$2342,6,) -> R1013 | Q11: =VLOOKUP(A11,'Hospitalisation Details'!$L$2:$R$2342,3,) -> 44 | R11: =VLOOKUP(A11,'Hospitalisation Details'!$L$2:$U$2342,10,) -> 29 | S11: =VLOOKUP(A11,'Hospitalisation Details'!$L$2:$U$2342,8,) -> Dec | T11: =VLOOKUP(A11,'Hospitalisation Details'!$L$2:$U$2342,9,) -> 1978
A12: Id11 | B12: =VLOOKUP(A12,'Medical Examinations'!$AS$1:$BC$2336,9,) -> Paola Andrea | C12: =VLOOKUP(A12,'Medical Examinations'!$AS$1:$BC$2336,2,) -> 37.7 | D12: =VLOOKUP(A12,'Medical Examinations'!$AS$1:$BC$2336,3,) -> 5.96 | E12: =VLOOKUP(A12,'Medical Examinations'!$AS$1:$BC$2336,6,) -> Yes | F12: =VLOOKUP(A12,'Medical Examinations'!$AS$1:$BC$2336,4,) -> No | G12: =VLOOKUP(A12,'Medical Examinations'!$AS$1:$BC$2336,5,) -> No | H12: =VLOOKUP(A12,'Medical Examinations'!$AS$1:$BC$2336,8,) -> 2 | I12: =VLOOKUP(A12,'Medical Examinations'!$AS$1:$BC$2336,7,) -> Yes | J12: =VLOOKUP(A12,'Medical Examinations'!$AS$1:$BC$2336,11,) -> Obesity | K12: =VLOOKUP(A12,'Medical Examinations'!$AS$1:$BC$2336,10,) -> Prediabetes | L12: =VLOOKUP(A12,'Hospitalisation Details'!$L$2:$R$2342,2,) -> 22-07-1959 | M12: =VLOOKUP(A12,'Hospitalisation Details'!$L$2:$R$2345,7,) -> 48824 | N12: =VLOOKUP(A12,'Hospitalisation Details'!$L$2:$R$2342,4,) -> tier - 2 | O12: =VLOOKUP(A12,'Hospitalisation Details'!$L$2:$R$2342,5,) -> tier - 1 | P12: =VLOOKUP(A12,'Hospitalisation Details'!$L$2:$R$2342,6,) -> R1011 | Q12: =VLOOKUP(A12,'Hospitalisation Details'!$L$2:$R$2342,3,) -> 63 | R12: =VLOOKUP(A12,'Hospitalisation Details'!$L$2:$U$2342,10,) -> 22 | S12: =VLOOKUP(A12,'Hospitalisation Details'!$L$2:$U$2342,8,) -> Jul | T12: =VLOOKUP(A12,'Hospitalisation Details'!$L$2:$U$2342,9,) -> 1959
A13: Id12 | B13: =VLOOKUP(A13,'Medical Examinations'!$AS$1:$BC$2336,9,) -> David | C13: =VLOOKUP(A13,'Medical Examinations'!$AS$1:$BC$2336,2,) -> 42.13 | D13: =VLOOKUP(A13,'Medical Examinations'!$AS$1:$BC$2336,3,) -> 11.9 | E13: =VLOOKUP(A13,'Medical Examinations'!$AS$1:$BC$2336,6,) -> No | F13: =VLOOKUP(A13,'Medical Examinations'!$AS$1:$BC$2336,4,) -> No | G13: =VLOOKUP(A13,'Medical Examinations'!$AS$1:$BC$2336,5,) -> No | H13: =VLOOKUP(A13,'Medical Examinations'!$AS$1:$BC$2336,8,) -> 0 | I13: =VLOOKUP(A13,'Medical Examinations'!$AS$1:$BC$2336,7,) -> Yes | J13: =VLOOKUP(A13,'Medical Examinations'!$AS$1:$BC$2336,11,) -> Obesity | K13: =VLOOKUP(A13,'Medical Examinations'!$AS$1:$BC$2336,10,) -> Diabetes | L13: =VLOOKUP(A13,'Hospitalisation Details'!$L$2:$R$2342,2,) -> 27-10-1965 | M13: =VLOOKUP(A13,'Hospitalisation Details'!$L$2:$R$2345,7,) -> 48676 | N13: =VLOOKUP(A13,'Hospitalisation Details'!$L$2:$R$2342,4,) -> tier - 1 | O13: =VLOOKUP(A13,'Hospitalisation Details'!$L$2:$R$2342,5,) -> tier - 2 | P13: =VLOOKUP(A13,'Hospitalisation Details'!$L$2:$R$2342,6,) -> R1013 | Q13: =VLOOKUP(A13,'Hospitalisation Details'!$L$2:$R$2342,3,) -> 57 | R13: =VLOOKUP(A13,'Hospitalisation Details'!$L$2:$U$2342,10,) -> 27 | S13: =VLOOKUP(A13,'Hospitalisation Details'!$L$2:$U$2342,8,) -> Oct | T13: =VLOOKUP(A13,'Hospitalisation Details'!$L$2:$U$2342,9,) -> 1965
... A2336: Id2335 | B2336: =VLOOKUP(A2336,'Medical Examinations'!$AS$1:$BC$2336,9,) -> Aaron K | C2336: =VLOOKUP(A2336,'Medical Examinations'!$AS$1:$BC$2336,2,) -> 17.58 | D2336: =VLOOKUP(A2336,'Medical Examinations'!$AS$1:$BC$2336,3,) -> 4.51 | E2336: =VLOOKUP(A2336,'Medical Examinations'!$AS$1:$BC$2336,6,) -> No | F2336: =VLOOKUP(A2336,'Medical Examinations'!$AS$1:$BC$2336,4,) -> No | G2336: =VLOOKUP(A2336,'Medical Examinations'!$AS$1:$BC$2336,5,) -> No | H2336: =VLOOKUP(A2336,'Medical Examinations'!$AS$1:$BC$2336,8,) -> 1 | I2336: =VLOOKUP(A2336,'Medical Examinations'!$AS$1:$BC$2336,7,) -> No | J2336: =VLOOKUP(A2336,'Medical Examinations'!$AS$1:$BC$2336,11,) -> Under weight | K2336: =VLOOKUP(A2336,'Medical Examinations'!$AS$1:$BC$2336,10,) -> Normal | L2336: =VLOOKUP(A2336,'Hospitalisation Details'!$L$2:$R$2342,2,) -> 09-07-1992 | M2336: =VLOOKUP(A2336,'Hospitalisation Details'!$L$2:$R$2345,7,) -> 564 | N2336: =VLOOKUP(A2336,'Hospitalisation Details'!$L$2:$R$2342,4,) -> tier - 2 | O2336: =VLOOKUP(A2336,'Hospitalisation Details'!$L$2:$R$2342,5,) -> tier - 3 | P2336: =VLOOKUP(A2336,'Hospitalisation Details'!$L$2:$R$2342,6,) -> R1013 | Q2336: =VLOOKUP(A2336,'Hospitalisation Details'!$L$2:$R$2342,3,) -> 30 | R2336: =VLOOKUP(A2336,'Hospitalisation Details'!$L$2:$U$2342,10,) -> 9 | S2336: =VLOOKUP(A2336,'Hospitalisation Details'!$L$2:$U$2342,8,) -> Jul | T2336: =VLOOKUP(A2336,'Hospitalisation Details'!$L$2:$U$2342,9,) -> 1992

Sheet Pie & Donut Chart
A3: Cancer History Status | B3: Customer Count | C3: Count of Smoker
A4: No | B4: 1944 | C4: 1944
A5: Yes | B5: 391 | C5: 391
E26: Smokers show a higher proportion of cancer history compared to non-smokers, indicating smoking as a major health risk factor.

Sheet Column Chart
A1: Row Labels | B1: Average of Charges
A2: Normal Weight | B2: 9851.9153
A3: Obesity | B3: 16661.464
A4: Over weight | B4: 11435.419
A5: Under weight | B5: 6899.3352
D28: Obese and overweight patients incur significantly higher healthcare charges compared to normal weight individuals

Sheet Count Of Cust&Hospitalisation 
A3: Row Labels | B3: Count of Customer ID | C3: Sum of Number of Major Surgeries
A4: Diabetes | B4: 784 | C4: 465
A5: Normal | B5: 1095 | C5: 778
A6: Prediabetes | B6: 456 | C6: 336
A7: Grand Total | B7: 2335 | C7: 1579

Sheet healthcare costs
A3: Row Labels | B3: Sum of Charges
A4: Normal Weight | B4: 4305287
A5: Obesity | B5: 20343647
A6: Over weight | B6: 5729145
A7: Under weight | B7: 1214283
A8: Grand Total | B8: 31592362

Sheet Average costs  medical metrics 
A3: Row Labels | B3: Average of Charges | C3: Average of BMI | D3: Average of HBA1C
A4: Normal Weight | B4: 9851.9153 | C4: 22.085057 | D4: 6.4814416
A5: Obesity | B5: 16661.464 | C5: 37.595536 | D5: 6.6199672
A6: Over weight | B6: 11435.419 | C6: 27.528363 | D6: 6.5097006
A7: Under weight | B7: 6899.3352 | C7: 16.898324 | D7: 6.7342614
A8: Grand Total | B8: 13529.919 | C8: 30.972649 | D8: 6.5789979

Sheet Quick Analysis
A3: Row Labels | B3: Total Customers | C3: Total hospitalisation count | D3: Total healthcare costs | E3: Average costs | F3: Average of HBA1C | G3: Average of BMI | H3: Average of Age
A4: Diabetes | B4: 784 | C4: 465 | D4: 12638312 | E4: 16120.296 | F4: 9.308699 | G4: 30.972385 | H4: 49.168367
A5: Normal | B5: 1095 | C5: 778 | D5: 13239342 | E5: 12090.723 | F5: 4.8492694 | G5: 30.980909 | H5: 34.123288
A6: Prediabetes | B6: 456 | C6: 336 | D6: 5714708 | E6: 12532.254 | F6: 6.0394518 | G6: 30.953268 | H6: 34.399123

Sheet Dynamic Analysis
E1: HealthCare Dynamic analysis

Sheet DASHBOARD
C1: AI-Generated Healthcare Summary
